{"symbol": "2050.SR", "name": "Savola Group Company", "description": "Savola Group Company, together with its subsidiaries, produces, markets, and distributes food products. It operates through five segments: Food Processing, Retail, Food Services, Frozen Food, and Investments. The company offers edible oils, sugar, pasta, spices, nuts, pulses, and other food products. It also engages in the agro cultivation, services and maintenance, retail, trading and distribution, wholesale and retail distribution of frozen food products, trading and distribution of seafood products, restaurant, renewable energy, e-commerce, and real estate activities, as well as investments in equity-accounted investees and other investments activities. In addition, it retails grocery products through a network of hyper markets, supermarkets, and convenience stores. Savola Group Company was founded in 1978 and is headquartered in Jeddah, the Kingdom of Saudi Arabia.", "sector": "Consumer Defensive", "industry": "Packaged Foods", "employees": null, "website": "https://www.savola.com", "city": "Jeddah", "country": "Saudi Arabia", "currency": "SAR", "exchange": "SAU", "price": 24.670000076293945, "change": -0.020000457763671875, "changePercent": -0.08100630753767323, "dayLow": 24.600000381469727, "dayHigh": 24.8799991607666, "volume": 315290, "open": 24.780000686645508, "previousClose": 24.690000534057617, "marketCap": 7357921792, "trailingPE": 2.0924513, "forwardPE": 15.515723, "peRatio": 2.0924513, "trailingEps": 11.79, "eps": 11.79, "dividendYield": null, "trailingAnnualDividendYield": 0.06885379, "dividendRate": null, "trailingAnnualDividendRate": 1.7, "payoutRatio": 0.0, "lastDividendValue": 1.461792, "lastDividendDate": 1683763200, "priceToBook": 1.3297758, "profitMargins": 0.03353, "beta": 0.455, "fiftyTwoWeekHigh": 32.65, "fiftyTwoWeekLow": 20.45, "fiftyTwoWeekChange": -0.18380165, "averageVolume": 678279, "fiftyDayAverage": 22.992, "twoHundredDayAverage": 24.3921, "sharesOutstanding": 298253836, "floatShares": 218608806, "sharesShort": null, "shortRatio": null, "heldPercentInstitutions": 0.30137, "heldPercentInsiders": 0.08602, "totalRevenue": 26081052672, "revenuePerShare": 87.348, "revenueGrowth": 0.215, "grossProfits": 5020141056, "grossMargins": 0.19248, "operatingMargins": -0.01263, "ebitda": 1742256000, "ebitdaMargins": 0.0668, "netIncomeToCommon": 882046976, "earningsGrowth": -0.982, "returnOnEquity": 0.15755999, "returnOnAssets": 0.03314, "operatingCashflow": 1068654016, "freeCashflow": -8032625, "totalCash": 989939008, "totalCashPerShare": 3.33, "totalDebt": 5846154752, "debtToEquity": 90.413, "currentRatio": 0.93, "quickRatio": 0.378, "bookValue": 18.552, "enterpriseValue": 13147129856, "enterpriseToEbitda": 7.546, "priceToSalesTrailing12Months": 0.28211752, "recommendationMean": 2.33333, "recommendationKey": "buy", "numberOfAnalystOpinions": 9, "targetLowPrice": 23.8, "targetMeanPrice": 30.61111, "targetMedianPrice": 34.0, "targetHighPrice": 37.0, "recommendationTrend": null, "lastUpdated": "2026-03-24T08:27:29.756393+00:00Z"}