{"symbol": "2330.TW", "name": "Taiwan Semiconductor Manufacturing Company Limited", "description": "Taiwan Semiconductor Manufacturing Company Limited, together with its subsidiaries, manufactures, packages, tests, and sells integrated circuits and other semiconductor devices in Taiwan, China, Europe, the Middle East, Africa, Japan, the United States, and internationally. It provides various wafer fabrication processes, such as processes to manufacture complementary metal- oxide-semiconductor (CMOS) logic, mixed-signal, radio frequency, embedded memory, bipolar CMOS mixed-signal, and others. The company also involved in providing customer and engineering support services; manufacturing of masks; investment in technology start-up companies; research, designing, developing, manufacturing, packaging, testing, and sale of color filters; and investment activities. Its products are used in high performance computing, smartphones, Internet of things, automotive, and digital consumer electronics. Taiwan Semiconductor Manufacturing Company Limited was incorporated in 1987 and is headquartered in Hsinchu City, Taiwan.", "sector": "Technology", "industry": "Semiconductors", "employees": 76907, "website": "https://www.tsmc.com", "city": "Hsinchu City", "country": "Taiwan", "currency": "TWD", "exchange": "TAI", "price": 2215.0, "change": -50.0, "changePercent": -2.207505518763797, "dayLow": 2215.0, "dayHigh": 2280.0, "volume": 52509163, "open": 2245.0, "previousClose": 2265.0, "marketCap": 57439378472960, "trailingPE": 30.09102, "forwardPE": 18.399555, "peRatio": 30.09102, "trailingEps": 73.61, "eps": 73.61, "dividendYield": 1.06, "trailingAnnualDividendYield": 0.007505519, "dividendRate": 24.0, "trailingAnnualDividendRate": 17.0, "payoutRatio": 0.2785, "lastDividendValue": 6.0, "lastDividendDate": 1781136000, "priceToBook": 9.750622, "profitMargins": 0.46505, "beta": 1.251, "fiftyTwoWeekHigh": 2330.0, "fiftyTwoWeekLow": 893.0, "fiftyTwoWeekChange": 1.5110865, "averageVolume": 37780306, "fiftyDayAverage": 1931.5, "twoHundredDayAverage": 1544.05, "sharesOutstanding": 25932000000, "floatShares": 24177670587, "sharesShort": null, "shortRatio": null, "heldPercentInstitutions": 0.41512, "heldPercentInsiders": 0.00022, "totalRevenue": 4103903379456, "revenuePerShare": 158.267, "revenueGrowth": 0.351, "grossProfits": 2539193892864, "grossMargins": 0.61873, "operatingMargins": 0.58105, "ebitda": 2856460222464, "ebitdaMargins": 0.69602996, "netIncomeToCommon": 1908519993344, "earningsGrowth": 0.584, "returnOnEquity": 0.3621, "returnOnAssets": 0.17322001, "operatingCashflow": 2348377702400, "freeCashflow": 721560469504, "totalCash": 3383600873472, "totalCashPerShare": 130.477, "totalDebt": 1016267997184, "debtToEquity": 17.131, "currentRatio": 2.488, "quickRatio": 2.186, "bookValue": 227.165, "enterpriseValue": 56411262287872, "enterpriseToEbitda": 19.749, "priceToSalesTrailing12Months": 13.99628, "recommendationMean": 1.33333, "recommendationKey": "strong_buy", "numberOfAnalystOpinions": 33, "targetLowPrice": 1740.0, "targetMeanPrice": 2508.6667, "targetMedianPrice": 2560.0, "targetHighPrice": 3000.0, "recommendationTrend": null, "lastUpdated": "2026-04-28T11:29:19.988565+00:00Z"}