{"symbol": "BP.L", "name": "BP p.l.c.", "description": "BP p.l.c., an integrated energy company, engages in the oil and gas business worldwide. The company operates through Gas & Low Carbon Energy, Oil Production & Operations, and Customers & Products segments. It engages in the production of natural gas, marketing, and trading activities, as well as solar, wind, and hydrogen businesses. The company also offers aviation fuel products and services, such as jet fuel; aviation gasoline; UL91 aviation fuel; and sustainable aviation fuel. In addition, it engages in the convenience and retail fuel; EV charging; Castrol lubricants and fluids; B2B; midstream; crude oil production; refining and oil trading; and bioenergy businesses. BP p.l.c. was founded in 1908 and is headquartered in London, the United Kingdom.", "sector": "Energy", "industry": "Oil & Gas Integrated", "employees": null, "website": "https://www.bp.com", "city": "London", "country": "United Kingdom", "currency": "GBp", "exchange": "LSE", "price": 460.45001220703125, "change": -5.29998779296875, "changePercent": -1.1379469228059582, "dayLow": 456.6499938964844, "dayHigh": 473.29998779296875, "volume": 27671524, "open": 466.1000061035156, "previousClose": 465.75, "marketCap": 70781771776, "trailingPE": "Infinity", "forwardPE": 12.366903, "peRatio": "Infinity", "trailingEps": 0.0, "eps": 0.0, "dividendYield": 5.24, "trailingAnnualDividendYield": 0.0007085347, "dividendRate": 0.24, "trailingAnnualDividendRate": 0.33, "payoutRatio": 95.140305, "lastDividendValue": 0.0832, "lastDividendDate": 1771459200, "priceToBook": 182.5043, "profitMargins": 0.00029, "beta": 0.055, "fiftyTwoWeekHigh": 481.35, "fiftyTwoWeekLow": 329.2, "fiftyTwoWeekChange": 0.0072448254, "averageVolume": 37623797, "fiftyDayAverage": 442.844, "twoHundredDayAverage": 420.13675, "sharesOutstanding": 15369959813, "floatShares": 14799682800, "sharesShort": null, "shortRatio": null, "heldPercentInstitutions": 0.34032002, "heldPercentInsiders": 0.00285, "totalRevenue": 187637006336, "revenuePerShare": 12.038, "revenueGrowth": 0.065, "grossProfits": 51350999040, "grossMargins": 0.27367002, "operatingMargins": 0.06495, "ebitda": 33840001024, "ebitdaMargins": 0.18035, "netIncomeToCommon": 54000000, "earningsGrowth": null, "returnOnEquity": 0.017, "returnOnAssets": 0.03494, "operatingCashflow": 24493000704, "freeCashflow": 5933000192, "totalCash": 36714000384, "totalCashPerShare": 2.383, "totalDebt": 72529002496, "debtToEquity": 98.012, "currentRatio": 1.263, "quickRatio": 0.793, "bookValue": 2.5229542, "enterpriseValue": 128533929984, "enterpriseToEbitda": 3.798, "priceToSalesTrailing12Months": 0.37722716, "recommendationMean": 2.6, "recommendationKey": "hold", "numberOfAnalystOpinions": 20, "targetLowPrice": 372.9487, "targetMeanPrice": 476.91977, "targetMedianPrice": 467.03024, "targetHighPrice": 594.7292, "recommendationTrend": null, "lastUpdated": "2026-02-17T21:07:30.891993+00:00Z"}