{"symbol": "DGE.L", "name": "Diageo plc", "description": "Diageo plc, together with its subsidiaries, engages in the production, marketing, and distribution of alcoholic beverages in North America, Europe, the Asia Pacific, Latin America and Caribbean, and Africa. It offers beer, scotch, gin, vodka, rum, liqueur, raki, wine, Irish and Canadian whisky, US and Indian whisky, Chinese whisky, cacha\u00e7a, tequila, brandy, and Chinese white spirit beverages. The company also provides ready-to-drink and non-alcoholic beverages. Its principal brands include Johnnie Walker, Don Julio, Guinness, Crown Royal, Smirnoff, Baileys, Captain Morgan, Casamigos, Shui Jing Fang, and McDowell's. The company was formerly known as Guinness plc and changed its name to Diageo plc in February 1998. The company was incorporated in 1886 and is headquartered in London, the United Kingdom.", "sector": "Consumer Defensive", "industry": "Beverages - Wineries & Distilleries", "employees": 29632, "website": "https://www.diageo.com", "city": "London", "country": "United Kingdom", "currency": "GBp", "exchange": "LSE", "price": 1755.5, "change": -4.5, "changePercent": -0.2556818181818182, "dayLow": 1755.5, "dayHigh": 1786.5, "volume": 3390528, "open": 1779.5, "previousClose": 1760.0, "marketCap": 39032467456, "trailingPE": 22.50641, "forwardPE": 14.305542, "peRatio": 22.50641, "trailingEps": 0.78, "eps": 0.78, "dividendYield": 4.52, "trailingAnnualDividendYield": 0.00058806816, "dividendRate": 0.79, "trailingAnnualDividendRate": 1.035, "payoutRatio": 0.9618, "lastDividendValue": 0.4791, "lastDividendDate": 1760572800, "priceToBook": 478.71674, "profitMargins": 0.116280004, "beta": 0.178, "fiftyTwoWeekHigh": 2226.0, "fiftyTwoWeekLow": 1421.5, "fiftyTwoWeekChange": -0.18912691, "averageVolume": 5461136, "fiftyDayAverage": 1657.22, "twoHundredDayAverage": 1850.8726, "sharesOutstanding": 2223438685, "floatShares": 2216526086, "sharesShort": null, "shortRatio": null, "heldPercentInstitutions": 0.65244, "heldPercentInsiders": 0.00074, "totalRevenue": 20245000192, "revenuePerShare": 9.111, "revenueGrowth": 0.004, "grossProfits": 12234999808, "grossMargins": 0.60435003, "operatingMargins": 0.27333, "ebitda": 6273999872, "ebitdaMargins": 0.3099, "netIncomeToCommon": 2353999872, "earningsGrowth": -0.747, "returnOnEquity": 0.20105, "returnOnAssets": 0.075500004, "operatingCashflow": 4296999936, "freeCashflow": 1689250048, "totalCash": 2647000064, "totalCashPerShare": 1.191, "totalDebt": 24611000320, "debtToEquity": 186.758, "currentRatio": 1.633, "quickRatio": 0.595, "bookValue": 3.6670954, "enterpriseValue": 63064940544, "enterpriseToEbitda": 10.052, "priceToSalesTrailing12Months": 1.9280053, "recommendationMean": 2.04348, "recommendationKey": "buy", "numberOfAnalystOpinions": 22, "targetLowPrice": 1457.4487, "targetMeanPrice": 2060.349, "targetMedianPrice": 1996.7644, "targetHighPrice": 2652.3374, "recommendationTrend": null, "lastUpdated": "2026-02-10T06:02:49.488217+00:00Z"}