{"symbol": "FTSEMIB.MI", "name": "FTSE MIB Index", "description": "No description available", "sector": "N/A", "industry": "N/A", "employees": null, "website": null, "city": null, "country": null, "currency": "EUR", "exchange": "MIL", "price": 47379.80078125, "change": 51.80078125, "changePercent": 0.10945060270875591, "dayLow": 47312.19140625, "dayHigh": 47440.5390625, "volume": 0, "open": 47392.98828125, "previousClose": 47328.0, "marketCap": null, "trailingPE": null, "forwardPE": null, "peRatio": null, "trailingEps": null, "eps": null, "dividendYield": null, "trailingAnnualDividendYield": null, "dividendRate": null, "trailingAnnualDividendRate": null, "payoutRatio": null, "lastDividendValue": null, "lastDividendDate": null, "priceToBook": null, "profitMargins": null, "beta": null, "fiftyTwoWeekHigh": 47651.0, "fiftyTwoWeekLow": 33581.0, "fiftyTwoWeekChange": 39.08546, "averageVolume": 518899304, "fiftyDayAverage": 45367.14, "twoHundredDayAverage": 43331.71, "sharesOutstanding": null, "floatShares": null, "sharesShort": null, "shortRatio": null, "heldPercentInstitutions": null, "heldPercentInsiders": null, "totalRevenue": null, "revenuePerShare": null, "revenueGrowth": null, "grossProfits": null, "grossMargins": null, "operatingMargins": null, "ebitda": null, "ebitdaMargins": null, "netIncomeToCommon": null, "earningsGrowth": null, "returnOnEquity": null, "returnOnAssets": null, "operatingCashflow": null, "freeCashflow": null, "totalCash": null, "totalCashPerShare": null, "totalDebt": null, "debtToEquity": null, "currentRatio": null, "quickRatio": null, "bookValue": null, "enterpriseValue": null, "enterpriseToEbitda": null, "priceToSalesTrailing12Months": null, "recommendationMean": null, "recommendationKey": null, "numberOfAnalystOpinions": null, "targetLowPrice": null, "targetMeanPrice": null, "targetMedianPrice": null, "targetHighPrice": null, "recommendationTrend": null, "lastUpdated": "2026-04-10T08:00:55.995308+00:00Z"}