{"symbol": "G.MI", "name": "Assicurazioni Generali S.p.A.", "description": "Assicurazioni Generali S.p.A. provides various insurance solutions under the Generali brand in the Americas, Italy, rest of Europe, Africa, the Middle East, Asia, and the Oceania. It operates through Life, Property & Casualty, and Asset & Wealth Management segments. The company offers savings, individual and family protection, and unit linked products, as well as motor third-party liability, home, property and casualty, accident, health, and commercial and industrial risks insurance products; and insurance plans for multinational companies. It also provides equity and fixed-income funds, and alternative products. The company was formerly known as Assicurazioni Generali Austro-Italiche and changed its name to Assicurazioni Generali S.p.A. in 1848. Assicurazioni Generali S.p.A. was founded in 1831 and is based in Trieste, Italy.", "sector": "Financial Services", "industry": "Insurance - Diversified", "employees": 87909, "website": "https://www.generali.com", "city": "Trieste", "country": "Italy", "currency": "EUR", "exchange": "MIL", "price": 33.75, "change": 0.25, "changePercent": 0.7462686567164178, "dayLow": 33.63999938964844, "dayHigh": 33.9900016784668, "volume": 1676560, "open": 33.79999923706055, "previousClose": 33.5, "marketCap": 50764046336, "trailingPE": 13.339921, "forwardPE": 11.014545, "peRatio": 13.339921, "trailingEps": 2.53, "eps": 2.53, "dividendYield": 4.27, "trailingAnnualDividendYield": 0.042686567, "dividendRate": 1.43, "trailingAnnualDividendRate": 1.43, "payoutRatio": 0.56520003, "lastDividendValue": 1.43, "lastDividendDate": 1747612800, "priceToBook": 1.7243141, "profitMargins": 0.06734, "beta": 0.692, "fiftyTwoWeekHigh": 36.4, "fiftyTwoWeekLow": 28.17, "fiftyTwoWeekChange": 0.13559318, "averageVolume": 2291614, "fiftyDayAverage": 34.5826, "twoHundredDayAverage": 32.992, "sharesOutstanding": 1503178000, "floatShares": 935499751, "sharesShort": null, "shortRatio": null, "heldPercentInstitutions": 0.33503, "heldPercentInsiders": 0.23010999, "totalRevenue": 56787001344, "revenuePerShare": 37.244, "revenueGrowth": 0.056, "grossProfits": 12042999808, "grossMargins": 0.21207, "operatingMargins": 0.14842, "ebitda": 8227999744, "ebitdaMargins": 0.14489001, "netIncomeToCommon": 3856000000, "earningsGrowth": 0.068, "returnOnEquity": 0.13393, "returnOnAssets": 0.0090499995, "operatingCashflow": 18837999616, "freeCashflow": 5084024832, "totalCash": 8778000384, "totalCashPerShare": 5.781, "totalDebt": 38651998208, "debtToEquity": 119.751, "currentRatio": 2.634, "quickRatio": 2.119, "bookValue": 19.573, "enterpriseValue": 83298787328, "enterpriseToEbitda": 10.124, "priceToSalesTrailing12Months": 0.89393777, "recommendationMean": 2.35294, "recommendationKey": "buy", "numberOfAnalystOpinions": 17, "targetLowPrice": 27.0, "targetMeanPrice": 35.80154, "targetMedianPrice": 37.0, "targetHighPrice": 42.0, "recommendationTrend": null, "lastUpdated": "2026-01-22T16:57:55.797890+00:00Z"}