{"symbol": "LONN.SW", "name": "Lonza Group AG", "description": "Lonza Group AG, together with its subsidiaries, operates as a contract development and manufacturing organization for pharma and biotech companies in Europe, North and Central America, Latin America, Asia, Australia, New Zealand, and internationally. It operates through Integrated Biologics; Advanced Synthesis; and Specialized Modalities segments. The Integrated Biologics segment offers CDMO biologics services from clinical development, drug substance, and drug product manufacturing; and operates mammalian and drug product platforms. Its Advanced Synthesis segment manufactures antibody-drug conjugates (ADCs) and other bioconjugates, small molecules, and highly potent active pharmaceutical ingredients; and operates small molecules and bioconjugates platforms. The Specialized Modalities segment operates various technologies, such as spanning cell & gene, microbial, bioscience, and mRNA. Lonza Group AG was incorporated in 1897 and is headquartered in Basel, Switzerland.", "sector": "Healthcare", "industry": "Diagnostics & Research", "employees": 20000, "website": "https://www.lonza.com", "city": "Basel", "country": "Switzerland", "currency": "CHF", "exchange": "EBS", "price": 490.20001220703125, "change": 11.0, "changePercent": 2.2954924290042826, "dayLow": 479.0, "dayHigh": 494.3999938964844, "volume": 215426, "open": 479.0, "previousClose": 479.20001220703125, "marketCap": 34237642752, "trailingPE": 37.73672, "forwardPE": 22.637077, "peRatio": 37.73672, "trailingEps": 12.99, "eps": 12.99, "dividendYield": 1.02, "trailingAnnualDividendYield": 0.010434057, "dividendRate": 5.0, "trailingAnnualDividendRate": 5.0, "payoutRatio": 0.3077, "lastDividendValue": 5.0, "lastDividendDate": 1778544000, "priceToBook": 4.326758, "profitMargins": -0.04211, "beta": 0.819, "fiftyTwoWeekHigh": 594.8, "fiftyTwoWeekLow": 454.6, "fiftyTwoWeekChange": -0.15160954, "averageVolume": 177581, "fiftyDayAverage": 502.578, "twoHundredDayAverage": 534.7955, "sharesOutstanding": 69844229, "floatShares": 69810005, "sharesShort": null, "shortRatio": null, "heldPercentInstitutions": 0.58704, "heldPercentInsiders": 0.00090000004, "totalRevenue": 6530999808, "revenuePerShare": 93.27, "revenueGrowth": null, "grossProfits": 2348999936, "grossMargins": 0.35966998, "operatingMargins": 0.2139, "ebitda": 2136999936, "ebitdaMargins": 0.32721, "netIncomeToCommon": 909000000, "earningsGrowth": null, "returnOnEquity": 0.10476, "returnOnAssets": 0.04639, "operatingCashflow": 1156000000, "freeCashflow": -1798875008, "totalCash": 719000000, "totalCashPerShare": 10.294, "totalDebt": 4679000064, "debtToEquity": 58.737, "currentRatio": 1.885, "quickRatio": 0.624, "bookValue": 113.295, "enterpriseValue": 38250639360, "enterpriseToEbitda": 17.899, "priceToSalesTrailing12Months": 5.242328, "recommendationMean": 1.54167, "recommendationKey": "buy", "numberOfAnalystOpinions": 23, "targetLowPrice": 550.0, "targetMeanPrice": 673.6087, "targetMedianPrice": 670.0, "targetHighPrice": 815.0, "recommendationTrend": null, "lastUpdated": "2026-05-06T04:02:04.140450+00:00Z"}