{"symbol": "NOVN.SW", "name": "Novartis AG", "description": "Novartis AG researches, develops, manufactures, distributes, markets, and sells pharmaceutical medicines in Switzerland and internationally. The company offers Entresto, an angiotensin receptorneprilysin inhibitor to treat symptomatic chronic heart failure with reduced ejection fraction (HFrEF); Cosentyx to treat plaque psoriasis, pso riatic arthritis, ankylosing spondylitis, and nonradiographic axial spondy loarthritis; Kisqali, a selective oral cyclin dependent inhibitor of kinases 4 and 6 (CDK4/6); Promacta/Revolade to treat immune thrombocytopenia (ITP), thrombocytopenia, and patients with severe aplastic anemia (SAA); Tafinlar+Mekinist, an oral combination therapy to treat patients with certain types of cancers; and Jakavi for the treatment of myelofibrosis, polycythemia vera, and acute or chronic graftversushost disease (GvHD). It also provides Tasigna to treat philadelphia chromosomepositive chronic myeloid leukemia in the chronic and/or accelerated phase; Xolair for the treatment of allergic asthma and nasal polyps or severe chronic rhinosi nusitis with nasal polyps; Ilaris to treat fever syndromes, Still's disease, and acute gouty arthritis; Pluvicto to treat prostatespecific membrane anti genpositive metastatic castrationresistant prostate cancer; Sandostatin SC and Sandostatin LAR to treat acromegaly carcinoid tumors and other types of functional gastro intestinal and pancreatic neuroendocrine tumors; Zolgensma for the treatment of genetic root cause of spinal muscular atrophy; Lucentis; Leqvio to reduce LDL cholesterol; Lutathera; Scemblix; and Fabhalta. The company focuses on therapeutic areas, such as cardiovascular, renal and metabolic, immunology, neuroscience, oncology, and hematology. It has a license and collaboration agreement with Alnylam Pharmaceuticals, Inc. to develop, manufacture, and commercialize Leqvio (inclisiran), a therapy to reduce LDL cholesterol. Novartis AG was incorporated in 1996 and is headquartered in Basel, Switzerland.", "sector": "Healthcare", "industry": "Drug Manufacturers - General", "employees": 75267, "website": "https://www.novartis.com", "city": "Basel", "country": "Switzerland", "currency": "CHF", "exchange": "EBS", "price": 115.9000015258789, "change": 2.5600051879882812, "changePercent": 2.258695315602765, "dayLow": 112.9000015258789, "dayHigh": 116.16000366210938, "volume": 3390647, "open": 113.37999725341797, "previousClose": 113.33999633789062, "marketCap": 221147856896, "trailingPE": 21.034483, "forwardPE": 14.86681, "peRatio": 21.034483, "trailingEps": 5.51, "eps": 5.51, "dividendYield": 3.19, "trailingAnnualDividendYield": 0.04116817, "dividendRate": 3.7, "trailingAnnualDividendRate": 4.666, "payoutRatio": 0.66260004, "lastDividendValue": 3.7, "lastDividendDate": 1773100800, "priceToBook": 6.0942063, "profitMargins": 0.23921, "beta": 0.522, "fiftyTwoWeekHigh": 131.0, "fiftyTwoWeekLow": 87.89, "fiftyTwoWeekChange": 0.24717534, "averageVolume": 3302123, "fiftyDayAverage": 120.8664, "twoHundredDayAverage": 109.7611, "sharesOutstanding": 1908091965, "floatShares": 1816121932, "sharesShort": null, "shortRatio": null, "heldPercentInstitutions": 0.44087002, "heldPercentInsiders": 0.02111, "totalRevenue": 56577998848, "revenuePerShare": 29.403, "revenueGrowth": -0.007, "grossProfits": 42746998784, "grossMargins": 0.75554, "operatingMargins": 0.30479, "ebitda": 22922000384, "ebitdaMargins": 0.40514, "netIncomeToCommon": 13534000128, "earningsGrowth": -0.093, "returnOnEquity": 0.34929, "returnOnAssets": 0.10541, "operatingCashflow": 19175000064, "freeCashflow": 12024750080, "totalCash": 6892000256, "totalCashPerShare": 3.612, "totalDebt": 46997999616, "debtToEquity": 120.734, "currentRatio": 0.848, "quickRatio": 0.526, "bookValue": 19.018063, "enterpriseValue": 261668864000, "enterpriseToEbitda": 11.416, "priceToSalesTrailing12Months": 3.9087253, "recommendationMean": 2.63636, "recommendationKey": "hold", "numberOfAnalystOpinions": 21, "targetLowPrice": 94.613434, "targetMeanPrice": 121.09854, "targetMedianPrice": 123.77864, "targetHighPrice": 139.4311, "recommendationTrend": null, "lastUpdated": "2026-05-02T18:57:21.498588+00:00Z"}