{"symbol": "SHELL.AS", "name": "Shell plc", "description": "Shell plc operates as an energy and petrochemical company Europe, Asia, Oceania, Africa, the United States, and other Americas. It operates through Integrated Gas; Upstream; Marketing; Chemicals and Products; and Renewables and Energy Solutions segments. The company explores for and extracts natural gas to produce liquefied natural gas or convert into gas-to-liquids products; explores for and extracts crude oil and natural gas liquids; and operates upstream and midstream infrastructure to deliver gas to market. It is also involved in marketing supplies fuels and lubricants for transport, manufacturing, mining, power generation, agriculture, and construction industries; operates electric vehicle charging and convenience retail; turn crude oil and other feedstocks into products for households, industry, and transport; trades crude oil, oil products, and petrochemicals; and oil sand activities. In addition, the company generates, markets, and trades power from wind, solar and pipeline gas; hydrogen production and marketing; commercial carbon capture and storage hubs; carbon credits and nature-based solutions; and provides heavy-duty LNG-fuelled trucks. Further, it offers base chemicals, including ethylene, propylene, and aromatics, as well as intermediate chemicals, such as styrene monomer, propylene oxide, solvents, linear alpha olefins, detergent alcohols, ethylene oxide, ethylene glycol, and polyethylene; and sustainable aviation fuel. The company was formerly known as Royal Dutch Shell plc and changed its name to Shell plc in January 2022. Shell plc was founded in 1897 and is headquartered in London, the United Kingdom.", "sector": "Energy", "industry": "Oil & Gas Integrated", "employees": null, "website": "https://www.shell.com", "city": "London", "country": "United Kingdom", "currency": "EUR", "exchange": "AMS", "price": 33.084999084472656, "change": -0.11500167846679688, "changePercent": -0.3463905898314651, "dayLow": 32.86000061035156, "dayHigh": 33.224998474121094, "volume": 4580650, "open": 33.165000915527344, "previousClose": 33.20000076293945, "marketCap": 186818560000, "trailingPE": 13.077075, "forwardPE": 10.606182, "peRatio": 13.077075, "trailingEps": 2.53, "eps": 2.53, "dividendYield": 3.81, "trailingAnnualDividendYield": 0.043554217, "dividendRate": 1.26, "trailingAnnualDividendRate": 1.446, "payoutRatio": 0.4773, "lastDividendValue": 0.372, "lastDividendDate": 1771459200, "priceToBook": 1.292301, "profitMargins": 0.06684, "beta": -0.107, "fiftyTwoWeekHigh": 34.215, "fiftyTwoWeekLow": 26.53, "fiftyTwoWeekChange": 0.019568563, "averageVolume": 5731022, "fiftyDayAverage": 31.4941, "twoHundredDayAverage": 31.136225, "sharesOutstanding": 5646624282, "floatShares": 5593594322, "sharesShort": null, "shortRatio": null, "heldPercentInstitutions": 0.37631, "heldPercentInsiders": 0.00041, "totalRevenue": 266886004736, "revenuePerShare": 45.306, "revenueGrowth": -0.033, "grossProfits": 67794001920, "grossMargins": 0.25402, "operatingMargins": 0.09811, "ebitda": 53257998336, "ebitdaMargins": 0.19955, "netIncomeToCommon": 17838000128, "earningsGrowth": 3.704, "returnOnEquity": 0.101940006, "returnOnAssets": 0.05065, "operatingCashflow": 42863001600, "freeCashflow": 21636249600, "totalCash": 30215999488, "totalCashPerShare": 5.264, "totalDebt": 75643002880, "debtToEquity": 43.146, "currentRatio": 1.3, "quickRatio": 0.908, "bookValue": 25.601618, "enterpriseValue": 236249989120, "enterpriseToEbitda": 4.436, "priceToSalesTrailing12Months": 0.69999385, "recommendationMean": 2.14286, "recommendationKey": "buy", "numberOfAnalystOpinions": 6, "targetLowPrice": 31.0527, "targetMeanPrice": 34.356556, "targetMedianPrice": 34.097015, "targetHighPrice": 37.059673, "recommendationTrend": null, "lastUpdated": "2026-02-15T13:37:08.472333+00:00Z"}