{"symbol": "TTE.PA", "name": "TotalEnergies SE", "description": "TotalEnergies SE, a multi-energy company, produces and markets oil and biofuels, natural and green gas, biogas and low-carbon hydrogen, renewables, and electricity in France, rest of Europe, North America, Africa, and internationally. It operates through five segments: Exploration & Production, Integrated LNG, Integrated Power, Refining & Chemicals, and Marketing & Services. The Exploration & Production segment is involved in the exploration and production of oil and natural gas. The Integrated LNG segment comprises the integrated gas chain, including upstream and midstream liquified natural gas (LNG) activities, as well as biogas, hydrogen, and gas trading activities. The Integrated Power segment includes generation, storage, electricity trading, and B2B-B2C distribution of gas and electricity. The Refining & Chemicals segment is involved in refining, petrochemicals, and specialty chemicals, as well as oil supply, trading, and marine shipping activities. The Marketing & Services segment supplies and markets petroleum products. The company was formerly known as TOTAL SE and changed its name to TotalEnergies SE in June 2021. TotalEnergies SE was incorporated in 1924 and is headquartered in Courbevoie, France.", "sector": "Energy", "industry": "Oil & Gas Integrated", "employees": 95393, "website": "https://www.totalenergies.com", "city": "Courbevoie", "country": "France", "currency": "EUR", "exchange": "PAR", "price": 62.630001068115234, "change": 0.049999237060546875, "changePercent": 0.07989650942409411, "dayLow": 61.939998626708984, "dayHigh": 62.59000015258789, "volume": 2884467, "open": 61.959999084472656, "previousClose": 62.58000183105469, "marketCap": 134234783744, "trailingPE": 11.906844, "forwardPE": 11.078387, "peRatio": 11.906844, "trailingEps": 5.26, "eps": 5.26, "dividendYield": 5.43, "trailingAnnualDividendYield": 0.058836687, "dividendRate": 3.4, "trailingAnnualDividendRate": 3.682, "payoutRatio": 0.593, "lastDividendValue": 0.85, "lastDividendDate": 1774915200, "priceToBook": 1.3914378, "profitMargins": 0.07724, "beta": 0.253, "fiftyTwoWeekHigh": 63.06, "fiftyTwoWeekLow": 47.645, "fiftyTwoWeekChange": 0.06755376, "averageVolume": 3703257, "fiftyDayAverage": 57.0086, "twoHundredDayAverage": 53.980427, "sharesOutstanding": 2142507469, "floatShares": 1760116406, "sharesShort": null, "shortRatio": null, "heldPercentInstitutions": 0.45456, "heldPercentInsiders": 0.052750003, "totalRevenue": 183533993984, "revenuePerShare": 82.413, "revenueGrowth": -0.076, "grossProfits": 65988001792, "grossMargins": 0.35954, "operatingMargins": 0.1249, "ebitda": 35640999936, "ebitdaMargins": 0.19419001, "netIncomeToCommon": 14177000448, "earningsGrowth": 0.708, "returnOnEquity": 0.1223, "returnOnAssets": 0.04858, "operatingCashflow": 29379000320, "freeCashflow": 13277875200, "totalCash": 28298999808, "totalCashPerShare": 13.062, "totalDebt": 63940001792, "debtToEquity": 54.341, "currentRatio": 1.012, "quickRatio": 0.535, "bookValue": 45.010998, "enterpriseValue": 173601882112, "enterpriseToEbitda": 4.871, "priceToSalesTrailing12Months": 0.7313892, "recommendationMean": 1.95455, "recommendationKey": "buy", "numberOfAnalystOpinions": 22, "targetLowPrice": 51.833336, "targetMeanPrice": 62.21153, "targetMedianPrice": 62.241188, "targetHighPrice": 76.1657, "recommendationTrend": null, "lastUpdated": "2026-02-09T19:50:42.007352+00:00Z"}