{"symbol": "VALE3.SA", "name": "Vale S.A.", "description": "Vale S.A., together with its subsidiaries, produces iron ore and nickel in Asia, the Americas, Europe, and internationally. It operates through Iron Solutions and Energy Transition Materials segments. The company extracts and produces iron ore, iron ore pellets, briquettes, and other ferrous products; provides logistic related services; and operates mining complexes, railways, maritime terminals, and ports. It also produces nickel, copper, and cobalt, as well as by-products, such as gold, silver, platinum group metals, and other precious metals. In addition, the company engages in greenfield mineral exploration; invests in energy businesses through renewable sources; and operates pelletizing plants and distribution centers to support the delivery of iron ore. The company was formerly known as Companhia Vale do Rio Doce and changed its name to Vale S.A. in May 2009. Vale S.A. was founded in 1942 and is headquartered in Rio De Janeiro, Brazil.", "sector": "Basic Materials", "industry": "Other Industrial Metals & Mining", "employees": 65805, "website": "https://vale.com", "city": "Rio De Janeiro", "country": "Brazil", "currency": "BRL", "exchange": "SAO", "price": 86.80999755859375, "change": 3.3499984741210938, "changePercent": 4.013897089467313, "dayLow": 0.0, "dayHigh": 0.0, "volume": 0, "open": 0.0, "previousClose": 83.45999908447266, "marketCap": 370572787712, "trailingPE": 30.142359, "forwardPE": 7.553926, "peRatio": 30.142359, "trailingEps": 2.88, "eps": 2.88, "dividendYield": 7.94, "trailingAnnualDividendYield": 0.0651326, "dividendRate": 6.9, "trailingAnnualDividendRate": 5.477, "payoutRatio": 2.0855, "lastDividendValue": 3.581771, "lastDividendDate": 1765497600, "priceToBook": 2.010701, "profitMargins": 0.06467, "beta": 0.936, "fiftyTwoWeekHigh": 91.62, "fiftyTwoWeekLow": 0.0, "fiftyTwoWeekChange": 0.5063335, "averageVolume": 30373716, "fiftyDayAverage": 79.5452, "twoHundredDayAverage": 63.4019, "sharesOutstanding": 4268780141, "floatShares": 3967660390, "sharesShort": null, "shortRatio": null, "heldPercentInstitutions": 0.43814, "heldPercentInsiders": 0.06309, "totalRevenue": 213594996736, "revenuePerShare": 50.037, "revenueGrowth": 0.005, "grossProfits": 74708000768, "grossMargins": 0.34976003, "operatingMargins": 0.27639, "ebitda": 76863995904, "ebitdaMargins": 0.35986, "netIncomeToCommon": 13813999616, "earningsGrowth": null, "returnOnEquity": 0.05867, "returnOnAssets": 0.077870004, "operatingCashflow": 48765001728, "freeCashflow": 15446250496, "totalCash": 41628999680, "totalCashPerShare": 9.752, "totalDebt": 115859996672, "debtToEquity": 61.326, "currentRatio": 1.153, "quickRatio": 0.716, "bookValue": 43.174, "enterpriseValue": 449430814720, "enterpriseToEbitda": 5.847, "priceToSalesTrailing12Months": 1.734932, "recommendationMean": 2.35714, "recommendationKey": "buy", "numberOfAnalystOpinions": 12, "targetLowPrice": 70.37478, "targetMeanPrice": 85.611496, "targetMedianPrice": 85.858986, "targetHighPrice": 101.91851, "recommendationTrend": null, "lastUpdated": "2026-02-23T13:01:06.431716+00:00Z"}