{"symbol": "WDS.AX", "name": "Woodside Energy Group Ltd", "description": "Woodside Energy Group Ltd engages in the exploration, evaluation, development, production, marketing, and sale of hydrocarbons in the Asia Pacific, Africa, the Americas, and the Europe. It produces liquefied natural gas, pipeline gas, crude oil and condensate, and natural gas liquids. The company holds interests in the Pluto LNG, North West Shelf, Wheatstone and Julimar-Brunello, Bass Strait, Ngujima-Yin FPSO, Okha FPSO, Pyrenees FPSO, Macedon, Shenzi, Mad dog, Greater Angostura, as well as Scarborough, Sangomar, Trion, Calypso, Browse, Liard, Ruby, Sangomar, Atlantis, Woodside Solar opportunity, and Sunrise and Troubadour. It is also involved in the development of new energy products and lower-carbon services. The company was formerly known as Woodside Petroleum Ltd and changed its name to Woodside Energy Group Ltd in May 2022. Woodside Energy Group Ltd was founded in 1954 and is headquartered in Perth, Australia.", "sector": "Energy", "industry": "Oil & Gas E&P", "employees": 4718, "website": "https://www.woodside.com", "city": "Perth", "country": "Australia", "currency": "AUD", "exchange": "ASX", "price": 27.940000534057617, "change": 0.1900005340576172, "changePercent": 0.6846866092166385, "dayLow": 27.479999542236328, "dayHigh": 28.06999969482422, "volume": 1984515, "open": 27.600000381469727, "previousClose": 27.75, "marketCap": 53116739584, "trailingPE": 12.875576, "forwardPE": 19.834372, "peRatio": 12.875576, "trailingEps": 2.17, "eps": 2.17, "dividendYield": 6.01, "trailingAnnualDividendYield": 0.0, "dividendRate": 1.67, "trailingAnnualDividendRate": 0.0, "payoutRatio": 0.78980005, "lastDividendValue": 0.818179, "lastDividendDate": 1756339200, "priceToBook": 1.0584601, "profitMargins": 0.21420999, "beta": -0.07, "fiftyTwoWeekHigh": 28.07, "fiftyTwoWeekLow": 18.61, "fiftyTwoWeekChange": 0.17322493, "averageVolume": 4290989, "fiftyDayAverage": 24.3772, "twoHundredDayAverage": 24.50295, "sharesOutstanding": 1901100143, "floatShares": 1893642134, "sharesShort": null, "shortRatio": null, "heldPercentInstitutions": 0.42029998, "heldPercentInsiders": 0.00418, "totalRevenue": 13781000192, "revenuePerShare": 7.271, "revenueGrowth": 0.101, "grossProfits": 5506999808, "grossMargins": 0.39960998, "operatingMargins": 0.21745001, "ebitda": 8336000000, "ebitdaMargins": 0.60489, "netIncomeToCommon": 2952000000, "earningsGrowth": -0.322, "returnOnEquity": 0.080819994, "returnOnAssets": 0.03244, "operatingCashflow": 6792999936, "freeCashflow": 80875000, "totalCash": 5153999872, "totalCashPerShare": 2.714, "totalDebt": 13555000320, "debtToEquity": 35.201, "currentRatio": 1.9, "quickRatio": 1.625, "bookValue": 26.39684, "enterpriseValue": 63959306240, "enterpriseToEbitda": 7.673, "priceToSalesTrailing12Months": 3.8543458, "recommendationMean": 2.21429, "recommendationKey": "buy", "numberOfAnalystOpinions": 14, "targetLowPrice": 21.509989, "targetMeanPrice": 27.404198, "targetMedianPrice": 26.335749, "targetHighPrice": 41.908024, "recommendationTrend": null, "lastUpdated": "2026-02-25T01:01:34.966967+00:00Z"}