[
  {
    "symbol": "2222.SR",
    "name": "Saudi Arabian Oil Co.",
    "category": "SA",
    "country": "🇸🇦",
    "sector": null,
    "regularMarketPrice": 24.42,
    "price": 24.42,
    "regularMarketChange": -0.10000038,
    "change": -0.10000038,
    "regularMarketChangePercent": -0.40783188,
    "changePercent": -0.40783188,
    "regularMarketTime": "2025-12-07T12:18:35.000Z",
    "prevClose": 24.52,
    "high": 24.61,
    "low": 24.4,
    "volume": 2536819,
    "open": 24.52,
    "fiftyTwoWeekHigh": 29,
    "fiftyTwoWeekLow": 23.04,
    "marketCap": 5906091737088,
    "peRatio": 16.172186,
    "eps": 1.51,
    "dividendYield": 0.054037523,
    "lastUpdated": "2025-12-07T12:33:54.423Z"
  },
  {
    "symbol": "1120.SR",
    "name": "Al Rajhi Bank",
    "category": "SA",
    "country": "🇸🇦",
    "sector": null,
    "regularMarketPrice": 95.95,
    "price": 95.95,
    "regularMarketChange": -0.05000305,
    "change": -0.05000305,
    "regularMarketChangePercent": -0.052086513,
    "changePercent": -0.052086513,
    "regularMarketTime": "2025-12-07T12:18:25.000Z",
    "prevClose": 96,
    "high": 96.5,
    "low": 95.9,
    "volume": 935256,
    "open": 96,
    "fiftyTwoWeekHigh": 110,
    "fiftyTwoWeekLow": 87.8,
    "marketCap": 383799984128,
    "peRatio": 17.042627,
    "eps": 5.63,
    "dividendYield": 0.023020834,
    "lastUpdated": "2025-12-07T12:33:54.423Z"
  },
  {
    "symbol": "2010.SR",
    "name": "Saudi Basic Industries Corp.",
    "category": "SA",
    "country": "🇸🇦",
    "sector": null,
    "regularMarketPrice": 55.2,
    "price": 55.2,
    "regularMarketChange": 0.25,
    "change": 0.25,
    "regularMarketChangePercent": 0.45495903,
    "changePercent": 0.45495903,
    "regularMarketTime": "2025-12-07T12:16:57.000Z",
    "prevClose": 54.95,
    "high": 55.35,
    "low": 54.7,
    "volume": 336605,
    "open": 54.95,
    "fiftyTwoWeekHigh": 70.6,
    "fiftyTwoWeekLow": 53,
    "marketCap": 165600002048,
    "eps": -2.23,
    "dividendYield": 0.05823476,
    "lastUpdated": "2025-12-07T12:33:54.423Z"
  },
  {
    "symbol": "7010.SR",
    "name": "Saudi Telecom Co.",
    "category": "SA",
    "country": "🇸🇦",
    "sector": null,
    "regularMarketPrice": 42.1,
    "price": 42.1,
    "regularMarketChange": -0.22000122,
    "change": -0.22000122,
    "regularMarketChangePercent": -0.5198516,
    "changePercent": -0.5198516,
    "regularMarketTime": "2025-12-07T12:15:46.000Z",
    "prevClose": 42.32,
    "high": 42.48,
    "low": 42.08,
    "volume": 2654266,
    "open": 42.36,
    "fiftyTwoWeekHigh": 48.3,
    "fiftyTwoWeekLow": 39.8,
    "marketCap": 210070306816,
    "peRatio": 17.838984,
    "eps": 2.36,
    "dividendYield": 0.05198488,
    "lastUpdated": "2025-12-07T12:33:54.423Z"
  },
  {
    "symbol": "2082.SR",
    "name": "ACWA POWER Co.",
    "category": "SA",
    "country": "🇸🇦",
    "sector": null,
    "regularMarketPrice": 192,
    "price": 192,
    "regularMarketChange": 0,
    "change": 0,
    "regularMarketChangePercent": 0,
    "changePercent": 0,
    "regularMarketTime": "2025-12-07T12:18:16.000Z",
    "prevClose": 192,
    "high": 193.5,
    "low": 191.1,
    "volume": 97115,
    "open": 192,
    "fiftyTwoWeekHigh": 438.8,
    "fiftyTwoWeekLow": 186.2,
    "marketCap": 147091062784,
    "peRatio": 80,
    "eps": 2.4,
    "dividendYield": 0,
    "lastUpdated": "2025-12-07T12:33:54.423Z"
  },
  {
    "symbol": "1180.SR",
    "name": "The Saudi National Bank",
    "category": "SA",
    "country": "🇸🇦",
    "sector": null,
    "regularMarketPrice": 37.28,
    "price": 37.28,
    "regularMarketChange": 0.05999756,
    "change": 0.05999756,
    "regularMarketChangePercent": 0.1611971,
    "changePercent": 0.1611971,
    "regularMarketTime": "2025-12-07T12:16:05.000Z",
    "prevClose": 37.22,
    "high": 37.4,
    "low": 37.02,
    "volume": 3079003,
    "open": 37.38,
    "fiftyTwoWeekHigh": 41,
    "fiftyTwoWeekLow": 31.55,
    "marketCap": 221592305664,
    "peRatio": 9.558974,
    "eps": 3.9,
    "dividendYield": 0.05373455,
    "lastUpdated": "2025-12-07T12:33:54.423Z"
  },
  {
    "symbol": "2380.SR",
    "name": "Rabigh Refining and Petrochemic",
    "category": "SA",
    "country": "🇸🇦",
    "sector": null,
    "regularMarketPrice": 7.32,
    "price": 7.32,
    "regularMarketChange": 0.07000017,
    "change": 0.07000017,
    "regularMarketChangePercent": 0.9655196,
    "changePercent": 0.9655196,
    "regularMarketTime": "2025-12-07T12:18:14.000Z",
    "prevClose": 7.25,
    "high": 7.45,
    "low": 7.26,
    "volume": 1022348,
    "open": 7.34,
    "fiftyTwoWeekHigh": 9.48,
    "fiftyTwoWeekLow": 6.26,
    "marketCap": 16084712448,
    "eps": -2.44,
    "dividendYield": 0,
    "lastUpdated": "2025-12-07T12:33:54.423Z"
  },
  {
    "symbol": "4030.SR",
    "name": "National Shipping Company of Sa",
    "category": "SA",
    "country": "🇸🇦",
    "sector": null,
    "regularMarketPrice": 29.8,
    "price": 29.8,
    "regularMarketChange": 0.29999924,
    "change": 0.29999924,
    "regularMarketChangePercent": 1.0169466,
    "changePercent": 1.0169466,
    "regularMarketTime": "2025-12-07T12:18:15.000Z",
    "prevClose": 29.5,
    "high": 29.98,
    "low": 29.02,
    "volume": 127638,
    "open": 29.62,
    "fiftyTwoWeekHigh": 32.5,
    "fiftyTwoWeekLow": 20.64,
    "marketCap": 27500976128,
    "peRatio": 14.258373,
    "eps": 2.09,
    "dividendYield": 0.027118644,
    "lastUpdated": "2025-12-07T12:33:54.423Z"
  },
  {
    "symbol": "2350.SR",
    "name": "Saudi Kayan Petrochemical Co.",
    "category": "SA",
    "country": "🇸🇦",
    "sector": null,
    "regularMarketPrice": 5.22,
    "price": 5.22,
    "regularMarketChange": -0.03000021,
    "change": -0.03000021,
    "regularMarketChangePercent": -0.5714326,
    "changePercent": -0.5714326,
    "regularMarketTime": "2025-12-07T12:17:45.000Z",
    "prevClose": 5.25,
    "high": 5.32,
    "low": 5.2,
    "volume": 1621259,
    "open": 5.21,
    "fiftyTwoWeekHigh": 7.15,
    "fiftyTwoWeekLow": 4.46,
    "marketCap": 7829999616,
    "eps": -1.52,
    "dividendYield": 0,
    "lastUpdated": "2025-12-07T12:33:54.423Z"
  },
  {
    "symbol": "4200.SR",
    "name": "Aldrees Petroleum and Transport",
    "category": "SA",
    "country": "🇸🇦",
    "sector": null,
    "regularMarketPrice": 129.2,
    "price": 129.2,
    "regularMarketChange": 0.69999695,
    "change": 0.69999695,
    "regularMarketChangePercent": 0.54474473,
    "changePercent": 0.54474473,
    "regularMarketTime": "2025-12-07T12:18:31.000Z",
    "prevClose": 128.5,
    "high": 130,
    "low": 128.5,
    "volume": 144675,
    "open": 128.6,
    "fiftyTwoWeekHigh": 154.4,
    "fiftyTwoWeekLow": 109.6,
    "marketCap": 12919999488,
    "peRatio": 31.589241,
    "eps": 4.09,
    "dividendYield": 0.0116731515,
    "lastUpdated": "2025-12-07T12:33:54.423Z"
  },
  {
    "symbol": "1211.SR",
    "name": "Ma'aden",
    "category": "SA",
    "country": "🇸🇦",
    "sector": null,
    "regularMarketPrice": 58.95,
    "price": 58.95,
    "regularMarketChange": -0.5999985,
    "change": -0.5999985,
    "regularMarketChangePercent": -1.0075542,
    "changePercent": -1.0075542,
    "regularMarketTime": "2025-12-07T12:18:10.000Z",
    "prevClose": 59.55,
    "high": 60,
    "low": 58.8,
    "volume": 447788,
    "open": 60,
    "fiftyTwoWeekHigh": 68.45,
    "fiftyTwoWeekLow": 37.85,
    "marketCap": 228778868736,
    "peRatio": 38.27922,
    "eps": 1.54,
    "dividendYield": 0,
    "lastUpdated": "2025-12-07T12:33:54.423Z"
  },
  {
    "symbol": "4001.SR",
    "name": "Abdullah Al Othaim Markets Co.",
    "category": "SA",
    "country": "🇸🇦",
    "sector": null,
    "regularMarketPrice": 6.53,
    "price": 6.53,
    "regularMarketChange": -0.07999992,
    "change": -0.07999992,
    "regularMarketChangePercent": -1.2102863,
    "changePercent": -1.2102863,
    "regularMarketTime": "2025-12-07T12:18:33.000Z",
    "prevClose": 6.61,
    "high": 6.64,
    "low": 6.5,
    "volume": 1216088,
    "open": 6.61,
    "fiftyTwoWeekHigh": 11.02,
    "fiftyTwoWeekLow": 6.5,
    "marketCap": 5877000192,
    "peRatio": 13.893618,
    "eps": 0.47,
    "dividendYield": 0.06202723,
    "lastUpdated": "2025-12-07T12:33:54.423Z"
  },
  {
    "symbol": "2310.SR",
    "name": "Sahara International Petrochemi",
    "category": "SA",
    "country": "🇸🇦",
    "sector": null,
    "regularMarketPrice": 15.87,
    "price": 15.87,
    "regularMarketChange": -0.03999996,
    "change": -0.03999996,
    "regularMarketChangePercent": -0.25141397,
    "changePercent": -0.25141397,
    "regularMarketTime": "2025-12-07T12:18:38.000Z",
    "prevClose": 15.91,
    "high": 15.99,
    "low": 15.79,
    "volume": 1336198,
    "open": 15.93,
    "fiftyTwoWeekHigh": 25.7,
    "fiftyTwoWeekLow": 15.79,
    "marketCap": 11637999616,
    "eps": -0.58,
    "dividendYield": 0.06285355,
    "lastUpdated": "2025-12-07T12:33:54.423Z"
  },
  {
    "symbol": "4003.SR",
    "name": "United Electronics Co.",
    "category": "SA",
    "country": "🇸🇦",
    "sector": null,
    "regularMarketPrice": 88.4,
    "price": 88.4,
    "regularMarketChange": -0.15000153,
    "change": -0.15000153,
    "regularMarketChangePercent": -0.16939755,
    "changePercent": -0.16939755,
    "regularMarketTime": "2025-12-07T12:16:19.000Z",
    "prevClose": 88.55,
    "high": 88.7,
    "low": 87.95,
    "volume": 51549,
    "open": 88.55,
    "fiftyTwoWeekHigh": 100,
    "fiftyTwoWeekLow": 83.4,
    "marketCap": 6703042560,
    "peRatio": 13.965245,
    "eps": 6.33,
    "dividendYield": 0.05646527,
    "lastUpdated": "2025-12-07T12:33:54.423Z"
  },
  {
    "symbol": "2050.SR",
    "name": "Savola Group",
    "category": "SA",
    "country": "🇸🇦",
    "sector": null,
    "regularMarketPrice": 24,
    "price": 24,
    "regularMarketChange": -0.29999924,
    "change": -0.29999924,
    "regularMarketChangePercent": -1.2345648,
    "changePercent": -1.2345648,
    "regularMarketTime": "2025-12-07T12:18:03.000Z",
    "prevClose": 24.3,
    "high": 24.34,
    "low": 23.96,
    "volume": 464401,
    "open": 24.2,
    "fiftyTwoWeekHigh": 40.6,
    "fiftyTwoWeekLow": 22.52,
    "marketCap": 7158091776,
    "peRatio": 2.0356233,
    "eps": 11.79,
    "dividendYield": 0,
    "lastUpdated": "2025-12-07T12:33:54.423Z"
  },
  {
    "symbol": "1150.SR",
    "name": "Alinma",
    "category": "SA",
    "country": "🇸🇦",
    "sector": null,
    "regularMarketPrice": 24.32,
    "price": 24.32,
    "regularMarketChange": 0,
    "change": 0,
    "regularMarketChangePercent": 0,
    "changePercent": 0,
    "regularMarketTime": "2025-12-07T12:18:24.000Z",
    "prevClose": 24.32,
    "high": 24.41,
    "low": 24.26,
    "volume": 2125563,
    "open": 24.32,
    "fiftyTwoWeekHigh": 31.3,
    "fiftyTwoWeekLow": 23.94,
    "marketCap": 60412764160,
    "peRatio": 10.4827585,
    "eps": 2.32,
    "dividendYield": 0.049342107,
    "lastUpdated": "2025-12-07T12:33:54.423Z"
  },
  {
    "symbol": "4190.SR",
    "name": "Jarir Marketing Co.",
    "category": "SA",
    "country": "🇸🇦",
    "sector": null,
    "regularMarketPrice": 12.58,
    "price": 12.58,
    "regularMarketChange": -0.21000004,
    "change": -0.21000004,
    "regularMarketChangePercent": -1.641908,
    "changePercent": -1.641908,
    "regularMarketTime": "2025-12-07T12:17:50.000Z",
    "prevClose": 12.79,
    "high": 12.78,
    "low": 12.54,
    "volume": 787261,
    "open": 12.78,
    "fiftyTwoWeekHigh": 14.56,
    "fiftyTwoWeekLow": 12,
    "marketCap": 15095999488,
    "peRatio": 14.799999,
    "eps": 0.85,
    "dividendYield": 0.0179828,
    "lastUpdated": "2025-12-07T12:33:54.423Z"
  },
  {
    "symbol": "2290.SR",
    "name": "Yanbu National Petrochemical Co",
    "category": "SA",
    "country": "🇸🇦",
    "sector": null,
    "regularMarketPrice": 30.28,
    "price": 30.28,
    "regularMarketChange": -0.13999939,
    "change": -0.13999939,
    "regularMarketChangePercent": -0.46022153,
    "changePercent": -0.46022153,
    "regularMarketTime": "2025-12-07T12:16:45.000Z",
    "prevClose": 30.42,
    "high": 30.6,
    "low": 30.14,
    "volume": 200363,
    "open": 30.42,
    "fiftyTwoWeekHigh": 39.05,
    "fiftyTwoWeekLow": 28.25,
    "marketCap": 17032499200,
    "peRatio": 168.22221,
    "eps": 0.18,
    "dividendYield": 0.06574622,
    "lastUpdated": "2025-12-07T12:33:54.423Z"
  },
  {
    "symbol": "4002.SR",
    "name": "Mouwasat Medical Services Co.",
    "category": "SA",
    "country": "🇸🇦",
    "sector": null,
    "regularMarketPrice": 69.75,
    "price": 69.75,
    "regularMarketChange": -0.5,
    "change": -0.5,
    "regularMarketChangePercent": -0.7117438,
    "changePercent": -0.7117438,
    "regularMarketTime": "2025-12-07T12:17:39.000Z",
    "prevClose": 70.25,
    "high": 70.35,
    "low": 69.55,
    "volume": 197290,
    "open": 69.9,
    "fiftyTwoWeekHigh": 95.4,
    "fiftyTwoWeekLow": 65.6,
    "marketCap": 13950000128,
    "peRatio": 18.452381,
    "eps": 3.78,
    "dividendYield": 0.042704627,
    "lastUpdated": "2025-12-07T12:33:54.423Z"
  },
  {
    "symbol": "1010.SR",
    "name": "Riyad Bank",
    "category": "SA",
    "country": "🇸🇦",
    "sector": null,
    "regularMarketPrice": 26.5,
    "price": 26.5,
    "regularMarketChange": 0.65999985,
    "change": 0.65999985,
    "regularMarketChangePercent": 2.554179,
    "changePercent": 2.554179,
    "regularMarketTime": "2025-12-07T12:16:35.000Z",
    "prevClose": 25.84,
    "high": 26.6,
    "low": 25.84,
    "volume": 2270002,
    "open": 25.84,
    "fiftyTwoWeekHigh": 33.2,
    "fiftyTwoWeekLow": 25.3,
    "marketCap": 79368224768,
    "peRatio": 8.28125,
    "eps": 3.2,
    "dividendYield": 0.06772446,
    "lastUpdated": "2025-12-07T12:33:54.423Z"
  },
  {
    "symbol": "2020.SR",
    "name": "SABIC Agri",
    "category": "SA",
    "country": "🇸🇦",
    "sector": null,
    "regularMarketPrice": 115.7,
    "price": 115.7,
    "regularMarketChange": -0.30000305,
    "change": -0.30000305,
    "regularMarketChangePercent": -0.25862333,
    "changePercent": -0.25862333,
    "regularMarketTime": "2025-12-07T12:18:11.000Z",
    "prevClose": 116,
    "high": 116.2,
    "low": 115,
    "volume": 97132,
    "open": 116,
    "fiftyTwoWeekHigh": 125.7,
    "fiftyTwoWeekLow": 94.7,
    "marketCap": 55077294080,
    "peRatio": 12.841287,
    "eps": 9.01,
    "dividendYield": 0.056034483,
    "lastUpdated": "2025-12-07T12:33:54.423Z"
  },
  {
    "symbol": "2280.SR",
    "name": "Almarai",
    "category": "SA",
    "country": "🇸🇦",
    "sector": null,
    "regularMarketPrice": 44.14,
    "price": 44.14,
    "regularMarketChange": -0.060001373,
    "change": -0.060001373,
    "regularMarketChangePercent": -0.13574971,
    "changePercent": -0.13574971,
    "regularMarketTime": "2025-12-07T12:18:09.000Z",
    "prevClose": 44.2,
    "high": 44.2,
    "low": 43.82,
    "volume": 127227,
    "open": 44.16,
    "fiftyTwoWeekHigh": 61.5,
    "fiftyTwoWeekLow": 43.5,
    "marketCap": 43874770944,
    "peRatio": 18.239668,
    "eps": 2.42,
    "dividendYield": 0.022624435,
    "lastUpdated": "2025-12-07T12:33:54.423Z"
  },
  {
    "symbol": "5110.SR",
    "name": "Saudi Elec",
    "category": "SA",
    "country": "🇸🇦",
    "sector": null,
    "regularMarketPrice": 14.21,
    "price": 14.21,
    "regularMarketChange": 0.069999695,
    "change": 0.069999695,
    "regularMarketChangePercent": 0.49504736,
    "changePercent": 0.49504736,
    "regularMarketTime": "2025-12-07T12:15:05.000Z",
    "prevClose": 14.14,
    "high": 14.22,
    "low": 14.12,
    "volume": 292647,
    "open": 14.14,
    "fiftyTwoWeekHigh": 17.36,
    "fiftyTwoWeekLow": 13.72,
    "marketCap": 59207299072,
    "eps": -0.61,
    "dividendYield": 0.049504947,
    "lastUpdated": "2025-12-07T12:33:54.423Z"
  },
  {
    "symbol": "1140.SR",
    "name": "Albilad",
    "category": "SA",
    "country": "🇸🇦",
    "sector": null,
    "regularMarketPrice": 25.56,
    "price": 25.56,
    "regularMarketChange": -0.34000015,
    "change": -0.34000015,
    "regularMarketChangePercent": -1.3127419,
    "changePercent": -1.3127419,
    "regularMarketTime": "2025-12-07T12:17:42.000Z",
    "prevClose": 25.9,
    "high": 25.98,
    "low": 25.46,
    "volume": 620365,
    "open": 25.9,
    "fiftyTwoWeekHigh": 33.875,
    "fiftyTwoWeekLow": 23.38,
    "marketCap": 38339997696,
    "peRatio": 12.591133,
    "eps": 2.03,
    "dividendYield": 0,
    "lastUpdated": "2025-12-07T12:33:54.424Z"
  },
  {
    "symbol": "1060.SR",
    "name": "SAB الأول",
    "category": "SA",
    "country": "🇸🇦",
    "sector": null,
    "regularMarketPrice": 31.42,
    "price": 31.42,
    "regularMarketChange": 0.62000084,
    "change": 0.62000084,
    "regularMarketChangePercent": 2.0129898,
    "changePercent": 2.0129898,
    "regularMarketTime": "2025-12-07T12:13:20.000Z",
    "prevClose": 30.8,
    "high": 31.76,
    "low": 30.96,
    "volume": 1787693,
    "open": 31,
    "fiftyTwoWeekHigh": 38,
    "fiftyTwoWeekLow": 29.9,
    "marketCap": 64561643520,
    "peRatio": 7.9949107,
    "eps": 3.93,
    "dividendYield": 0.064935066,
    "lastUpdated": "2025-12-07T12:33:54.424Z"
  },
  {
    "symbol": "7200.SR",
    "name": "Al Moammar Information Systems ",
    "category": "SA",
    "country": "🇸🇦",
    "sector": null,
    "regularMarketPrice": 157.8,
    "price": 157.8,
    "regularMarketChange": 0.5,
    "change": 0.5,
    "regularMarketChangePercent": 0.31786397,
    "changePercent": 0.31786397,
    "regularMarketTime": "2025-12-07T12:16:17.000Z",
    "prevClose": 157.3,
    "high": 159.6,
    "low": 157,
    "volume": 18778,
    "open": 157,
    "fiftyTwoWeekHigh": 174.8,
    "fiftyTwoWeekLow": 118,
    "marketCap": 4734000128,
    "peRatio": 50.095238,
    "eps": 3.15,
    "dividendYield": 0.035600763,
    "lastUpdated": "2025-12-07T12:33:54.424Z"
  },
  {
    "symbol": "4220.SR",
    "name": "Emaar The Economic City",
    "category": "SA",
    "country": "🇸🇦",
    "sector": null,
    "regularMarketPrice": 11.29,
    "price": 11.29,
    "regularMarketChange": -0.10000038,
    "change": -0.10000038,
    "regularMarketChangePercent": -0.87796646,
    "changePercent": -0.87796646,
    "regularMarketTime": "2025-12-07T12:16:48.000Z",
    "prevClose": 11.39,
    "high": 11.43,
    "low": 11.2,
    "volume": 52579,
    "open": 11.35,
    "fiftyTwoWeekHigh": 19.7,
    "fiftyTwoWeekLow": 10.72,
    "marketCap": 5907604480,
    "eps": -3.08,
    "dividendYield": 0,
    "lastUpdated": "2025-12-07T12:33:54.424Z"
  },
  {
    "symbol": "4090.SR",
    "name": "Taiba Investments Co.",
    "category": "SA",
    "country": "🇸🇦",
    "sector": null,
    "regularMarketPrice": 34.6,
    "price": 34.6,
    "regularMarketChange": 0.019996643,
    "change": 0.019996643,
    "regularMarketChangePercent": 0.057827186,
    "changePercent": 0.057827186,
    "regularMarketTime": "2025-12-07T12:10:12.000Z",
    "prevClose": 34.58,
    "high": 34.7,
    "low": 34.36,
    "volume": 103420,
    "open": 34.58,
    "fiftyTwoWeekHigh": 51.5,
    "fiftyTwoWeekLow": 32.85,
    "marketCap": 9011828736,
    "peRatio": 23.221476,
    "eps": 1.49,
    "dividendYield": 0,
    "lastUpdated": "2025-12-07T12:33:54.424Z"
  },
  {
    "symbol": "4040.SR",
    "name": "Saudi Public Transport Co.",
    "category": "SA",
    "country": "🇸🇦",
    "sector": null,
    "regularMarketPrice": 10.32,
    "price": 10.32,
    "regularMarketChange": 0.009999275,
    "change": 0.009999275,
    "regularMarketChangePercent": 0.096986175,
    "changePercent": 0.096986175,
    "regularMarketTime": "2025-12-07T12:10:12.000Z",
    "prevClose": 10.31,
    "high": 10.41,
    "low": 10.26,
    "volume": 161495,
    "open": 10.29,
    "fiftyTwoWeekHigh": 22.2,
    "fiftyTwoWeekLow": 10.09,
    "marketCap": 1290000000,
    "peRatio": 1032,
    "eps": 0.01,
    "dividendYield": 0,
    "lastUpdated": "2025-12-07T12:33:54.424Z"
  },
  {
    "symbol": "^TASI.SR",
    "name": "Tadawul All Shares Index",
    "category": "SA",
    "country": "🇸🇦",
    "sector": null,
    "regularMarketPrice": 10631.25,
    "price": 10631.25,
    "regularMarketChange": 5.0996094,
    "change": 5.0996094,
    "regularMarketChangePercent": 0.047991127,
    "changePercent": 0.047991127,
    "regularMarketTime": "2025-12-07T12:18:44.000Z",
    "prevClose": 10626.15,
    "high": 10666.53,
    "low": 10612.2,
    "volume": 116588907,
    "open": 10640.01,
    "fiftyTwoWeekHigh": 13949.13,
    "fiftyTwoWeekLow": 9930.86,
    "lastUpdated": "2025-12-07T12:33:54.424Z"
  },
  {
    "symbol": "^GSPC",
    "name": "S&P 500",
    "category": "Global",
    "country": "🇺🇸",
    "sector": null,
    "regularMarketPrice": 6870.4,
    "price": 6870.4,
    "regularMarketChange": 13.279785,
    "change": 13.279785,
    "regularMarketChangePercent": 0.19366418,
    "changePercent": 0.19366418,
    "regularMarketTime": "2025-12-05T21:55:44.000Z",
    "prevClose": 6857.12,
    "high": 6895.78,
    "low": 6858.29,
    "volume": 3146162000,
    "open": 6866.32,
    "fiftyTwoWeekHigh": 6920.34,
    "fiftyTwoWeekLow": 4835.04,
    "lastUpdated": "2025-12-07T12:33:54.424Z"
  },
  {
    "symbol": "^DJI",
    "name": "Dow Jones",
    "category": "Global",
    "country": "🇺🇸",
    "sector": null,
    "regularMarketPrice": 47954.99,
    "price": 47954.99,
    "regularMarketChange": 104.046875,
    "change": 104.046875,
    "regularMarketChangePercent": 0.21743956,
    "changePercent": 0.21743956,
    "regularMarketTime": "2025-12-05T21:55:44.000Z",
    "prevClose": 47850.94,
    "high": 48133.54,
    "low": 47871.51,
    "volume": 459236439,
    "open": 47879.6,
    "fiftyTwoWeekHigh": 48431.57,
    "fiftyTwoWeekLow": 36611.78,
    "lastUpdated": "2025-12-07T12:33:54.424Z"
  },
  {
    "symbol": "^IXIC",
    "name": "Nasdaq",
    "category": "Global",
    "country": "🇺🇸",
    "sector": null,
    "regularMarketPrice": 23578.129,
    "price": 23578.129,
    "regularMarketChange": 72.99219,
    "change": 72.99219,
    "regularMarketChangePercent": 0.3105372,
    "changePercent": 0.3105372,
    "regularMarketTime": "2025-12-05T22:15:59.000Z",
    "prevClose": 23505.137,
    "high": 23680.031,
    "low": 23506,
    "volume": 7359531000,
    "open": 23567.77,
    "fiftyTwoWeekHigh": 24019.99,
    "fiftyTwoWeekLow": 14784.03,
    "lastUpdated": "2025-12-07T12:33:54.424Z"
  },
  {
    "symbol": "^FTSE",
    "name": "FTSE 100",
    "category": "Global",
    "country": "🇬🇧",
    "sector": null,
    "regularMarketPrice": 9667.01,
    "price": 9667.01,
    "regularMarketChange": -43.86035,
    "change": -43.86035,
    "regularMarketChangePercent": -0.45166242,
    "changePercent": -0.45166242,
    "regularMarketTime": "2025-12-05T16:35:30.000Z",
    "prevClose": 9710.87,
    "high": 9738.26,
    "low": 9667.01,
    "volume": 780878138,
    "open": 9710.87,
    "fiftyTwoWeekHigh": 9930.1,
    "fiftyTwoWeekLow": 7544.8,
    "lastUpdated": "2025-12-07T12:33:54.424Z"
  },
  {
    "symbol": "^GDAXI",
    "name": "DAX",
    "category": "Global",
    "country": "🇩🇪",
    "sector": null,
    "regularMarketPrice": 24028.14,
    "price": 24028.14,
    "regularMarketChange": 146.11133,
    "change": 146.11133,
    "regularMarketChangePercent": 0.6118045,
    "changePercent": 0.6118045,
    "regularMarketTime": "2025-12-05T17:00:00.000Z",
    "prevClose": 23882.03,
    "high": 24130.92,
    "low": 23929.26,
    "volume": 53550183,
    "open": 23942.73,
    "fiftyTwoWeekHigh": 24771.34,
    "fiftyTwoWeekLow": 18489.91,
    "lastUpdated": "2025-12-07T12:33:54.424Z"
  },
  {
    "symbol": "^N225",
    "name": "Nikkei 225",
    "category": "Global",
    "country": "🇯🇵",
    "sector": null,
    "regularMarketPrice": 50491.87,
    "price": 50491.87,
    "regularMarketChange": -536.5508,
    "change": -536.5508,
    "regularMarketChangePercent": -1.0514743,
    "changePercent": -1.0514743,
    "regularMarketTime": "2025-12-05T06:45:03.000Z",
    "prevClose": 51028.42,
    "high": 50634.85,
    "low": 50215.41,
    "volume": 137685000,
    "open": 50530.34,
    "fiftyTwoWeekHigh": 52636.87,
    "fiftyTwoWeekLow": 30792.74,
    "lastUpdated": "2025-12-07T12:33:54.424Z"
  },
  {
    "symbol": "BZ=F",
    "name": "Oil (Brent)",
    "category": "Global",
    "country": "🛢️",
    "sector": null,
    "regularMarketPrice": 63.39,
    "price": 63.39,
    "regularMarketChange": 0.5299988,
    "change": 0.5299988,
    "regularMarketChangePercent": 0.8431415,
    "changePercent": 0.8431415,
    "regularMarketTime": "2025-12-05T21:59:34.000Z",
    "prevClose": 62.86,
    "high": 64.08,
    "low": 63.07,
    "volume": 23199,
    "open": 62.8,
    "fiftyTwoWeekHigh": 82.63,
    "fiftyTwoWeekLow": 58.39,
    "lastUpdated": "2025-12-07T12:33:54.424Z"
  },
  {
    "symbol": "GC=F",
    "name": "Gold",
    "category": "Global",
    "country": "🥇",
    "sector": null,
    "regularMarketPrice": 4212.9,
    "price": 4212.9,
    "regularMarketChange": 1.1000977,
    "change": 1.1000977,
    "regularMarketChangePercent": 0.026119418,
    "changePercent": 0.026119418,
    "regularMarketTime": "2025-12-05T21:56:51.000Z",
    "prevClose": 4211.8,
    "high": 4290.5,
    "low": 4221.4,
    "volume": 190889,
    "open": 4204.1,
    "fiftyTwoWeekHigh": 4358,
    "fiftyTwoWeekLow": 2582.1,
    "lastUpdated": "2025-12-07T12:33:54.424Z"
  },
  {
    "symbol": "AAPL",
    "name": "Apple",
    "category": "Global",
    "country": "🇺🇸",
    "sector": null,
    "regularMarketPrice": 278.78,
    "price": 278.78,
    "regularMarketChange": -1.92001,
    "change": -1.92001,
    "regularMarketChangePercent": -0.684009,
    "changePercent": -0.684009,
    "regularMarketTime": "2025-12-05T21:00:01.000Z",
    "prevClose": 280.7,
    "high": 281.14,
    "low": 278.05,
    "volume": 45584026,
    "open": 280.54,
    "fiftyTwoWeekHigh": 288.62,
    "fiftyTwoWeekLow": 169.21,
    "marketCap": 4137203793920,
    "peRatio": 37.319946,
    "eps": 7.47,
    "dividendYield": 0.0036337725,
    "lastUpdated": "2025-12-07T12:33:54.424Z"
  },
  {
    "symbol": "MSFT",
    "name": "Microsoft",
    "category": "Global",
    "country": "🇺🇸",
    "sector": null,
    "regularMarketPrice": 483.16,
    "price": 483.16,
    "regularMarketChange": 2.32001,
    "change": 2.32001,
    "regularMarketChangePercent": 0.482491,
    "changePercent": 0.482491,
    "regularMarketTime": "2025-12-05T21:00:00.000Z",
    "prevClose": 480.84,
    "high": 483.4,
    "low": 478.8801,
    "volume": 22109742,
    "open": 482.5,
    "fiftyTwoWeekHigh": 555.45,
    "fiftyTwoWeekLow": 344.79,
    "marketCap": 3591408713728,
    "peRatio": 34.36415,
    "eps": 14.06,
    "dividendYield": 0.0070709595,
    "lastUpdated": "2025-12-07T12:33:54.424Z"
  },
  {
    "symbol": "GOOG",
    "name": "Alphabet",
    "category": "Global",
    "country": "🇺🇸",
    "sector": null,
    "regularMarketPrice": 322.09,
    "price": 322.09,
    "regularMarketChange": 3.69998,
    "change": 3.69998,
    "regularMarketChangePercent": 1.16209,
    "changePercent": 1.16209,
    "regularMarketTime": "2025-12-05T21:00:01.000Z",
    "prevClose": 318.39,
    "high": 323.83,
    "low": 319.985,
    "volume": 15469201,
    "open": 320,
    "fiftyTwoWeekHigh": 328.67,
    "fiftyTwoWeekLow": 142.66,
    "marketCap": 3888216801280,
    "peRatio": 31.733006,
    "eps": 10.15,
    "dividendYield": 0.003203618,
    "lastUpdated": "2025-12-07T12:33:54.424Z"
  },
  {
    "symbol": "AMZN",
    "name": "Amazon",
    "category": "Global",
    "country": "🇺🇸",
    "sector": null,
    "regularMarketPrice": 229.53,
    "price": 229.53,
    "regularMarketChange": 0.419998,
    "change": 0.419998,
    "regularMarketChangePercent": 0.183317,
    "changePercent": 0.183317,
    "regularMarketTime": "2025-12-05T21:00:01.000Z",
    "prevClose": 229.11,
    "high": 231.24,
    "low": 228.547,
    "volume": 31389664,
    "open": 230.38,
    "fiftyTwoWeekHigh": 258.6,
    "fiftyTwoWeekLow": 161.38,
    "marketCap": 2453725249536,
    "peRatio": 32.465347,
    "eps": 7.07,
    "dividendYield": 0,
    "lastUpdated": "2025-12-07T12:33:54.424Z"
  },
  {
    "symbol": "TSLA",
    "name": "Tesla",
    "category": "Global",
    "country": "🇺🇸",
    "sector": null,
    "regularMarketPrice": 455,
    "price": 455,
    "regularMarketChange": 0.519989,
    "change": 0.519989,
    "regularMarketChangePercent": 0.114414,
    "changePercent": 0.114414,
    "regularMarketTime": "2025-12-05T21:00:00.000Z",
    "prevClose": 454.48,
    "high": 458.87,
    "low": 451.66,
    "volume": 56190168,
    "open": 452.97,
    "fiftyTwoWeekHigh": 488.54,
    "fiftyTwoWeekLow": 214.25,
    "marketCap": 1513247735808,
    "peRatio": 311.64383,
    "eps": 1.46,
    "dividendYield": 0,
    "lastUpdated": "2025-12-07T12:33:54.424Z"
  },
  {
    "symbol": "NVDA",
    "name": "Nvidia",
    "category": "Global",
    "country": "🇺🇸",
    "sector": null,
    "regularMarketPrice": 182.41,
    "price": 182.41,
    "regularMarketChange": -0.970001,
    "change": -0.970001,
    "regularMarketChangePercent": -0.528957,
    "changePercent": -0.528957,
    "regularMarketTime": "2025-12-05T21:00:00.000Z",
    "prevClose": 183.38,
    "high": 184.66,
    "low": 180.91,
    "volume": 142982463,
    "open": 183.86,
    "fiftyTwoWeekHigh": 212.19,
    "fiftyTwoWeekLow": 86.62,
    "marketCap": 4441136693248,
    "peRatio": 45.263027,
    "eps": 4.03,
    "dividendYield": 0.00021812628,
    "lastUpdated": "2025-12-07T12:33:54.424Z"
  },
  {
    "symbol": "META",
    "name": "Meta",
    "category": "Global",
    "country": "🇺🇸",
    "sector": null,
    "regularMarketPrice": 673.42,
    "price": 673.42,
    "regularMarketChange": 11.89,
    "change": 11.89,
    "regularMarketChangePercent": 1.79734,
    "changePercent": 1.79734,
    "regularMarketTime": "2025-12-05T21:00:02.000Z",
    "prevClose": 661.53,
    "high": 673.73,
    "low": 662.415,
    "volume": 20920800,
    "open": 664.5,
    "fiftyTwoWeekHigh": 796.25,
    "fiftyTwoWeekLow": 479.8,
    "marketCap": 1697373618176,
    "peRatio": 29.757843,
    "eps": 22.63,
    "dividendYield": 0.003136668,
    "lastUpdated": "2025-12-07T12:33:54.424Z"
  },
  {
    "symbol": "NFLX",
    "name": "Netflix",
    "category": "Global",
    "country": "🇺🇸",
    "sector": null,
    "regularMarketPrice": 100.24,
    "price": 100.24,
    "regularMarketChange": -2.98,
    "change": -2.98,
    "regularMarketChangePercent": -2.88704,
    "changePercent": -2.88704,
    "regularMarketTime": "2025-12-05T21:00:00.000Z",
    "prevClose": 103.22,
    "high": 104.79,
    "low": 97.74,
    "volume": 132718362,
    "open": 98.69,
    "fiftyTwoWeekHigh": 134.115,
    "fiftyTwoWeekLow": 82.11,
    "marketCap": 424749268992,
    "peRatio": 41.766663,
    "eps": 2.4,
    "dividendYield": 0,
    "lastUpdated": "2025-12-07T12:33:54.424Z"
  },
  {
    "symbol": "AMD",
    "name": "AMD",
    "category": "Global",
    "country": "🇺🇸",
    "sector": null,
    "regularMarketPrice": 217.97,
    "price": 217.97,
    "regularMarketChange": 1.99001,
    "change": 1.99001,
    "regularMarketChangePercent": 0.921384,
    "changePercent": 0.921384,
    "regularMarketTime": "2025-12-05T21:00:00.000Z",
    "prevClose": 215.98,
    "high": 223.642,
    "low": 216.24,
    "volume": 32596457,
    "open": 217.165,
    "fiftyTwoWeekHigh": 267.08,
    "fiftyTwoWeekLow": 76.48,
    "marketCap": 354864234496,
    "peRatio": 113.52605,
    "eps": 1.92,
    "dividendYield": 0,
    "lastUpdated": "2025-12-07T12:33:54.424Z"
  },
  {
    "symbol": "INTC",
    "name": "Intel",
    "category": "Global",
    "country": "🇺🇸",
    "sector": null,
    "regularMarketPrice": 41.41,
    "price": 41.41,
    "regularMarketChange": 0.91,
    "change": 0.91,
    "regularMarketChangePercent": 2.24691,
    "changePercent": 2.24691,
    "regularMarketTime": "2025-12-05T21:00:01.000Z",
    "prevClose": 40.5,
    "high": 42.83,
    "low": 41.155,
    "volume": 98968275,
    "open": 41.155,
    "fiftyTwoWeekHigh": 44.02,
    "fiftyTwoWeekLow": 17.67,
    "marketCap": 197525700608,
    "peRatio": 690.1667,
    "eps": 0.06,
    "dividendYield": 0,
    "lastUpdated": "2025-12-07T12:33:54.424Z"
  },
  {
    "symbol": "JPM",
    "name": "JPMorgan",
    "category": "Global",
    "country": "🇺🇸",
    "sector": null,
    "regularMarketPrice": 315.04,
    "price": 315.04,
    "regularMarketChange": -1.06,
    "change": -1.06,
    "regularMarketChangePercent": -0.335336,
    "changePercent": -0.335336,
    "regularMarketTime": "2025-12-05T21:00:02.000Z",
    "prevClose": 316.1,
    "high": 318.48,
    "low": 314.68,
    "volume": 4599712,
    "open": 315.64,
    "fiftyTwoWeekHigh": 322.25,
    "fiftyTwoWeekLow": 202.16,
    "marketCap": 866282504192,
    "peRatio": 15.603765,
    "eps": 20.19,
    "dividendYield": 0.017557735,
    "lastUpdated": "2025-12-07T12:33:54.424Z"
  },
  {
    "symbol": "V",
    "name": "Visa",
    "category": "Global",
    "country": "🇺🇸",
    "sector": null,
    "regularMarketPrice": 331.24,
    "price": 331.24,
    "regularMarketChange": 4.13998,
    "change": 4.13998,
    "regularMarketChangePercent": 1.26566,
    "changePercent": 1.26566,
    "regularMarketTime": "2025-12-05T21:00:02.000Z",
    "prevClose": 327.1,
    "high": 334.11,
    "low": 326.3972,
    "volume": 4266137,
    "open": 326.83,
    "fiftyTwoWeekHigh": 375.51,
    "fiftyTwoWeekLow": 299,
    "marketCap": 642917597184,
    "peRatio": 32.47451,
    "eps": 10.2,
    "dividendYield": 0.0074594924,
    "lastUpdated": "2025-12-07T12:33:54.424Z"
  },
  {
    "symbol": "MA",
    "name": "Mastercard",
    "category": "Global",
    "country": "🇺🇸",
    "sector": null,
    "regularMarketPrice": 545.52,
    "price": 545.52,
    "regularMarketChange": 3.21002,
    "change": 3.21002,
    "regularMarketChangePercent": 0.591916,
    "changePercent": 0.591916,
    "regularMarketTime": "2025-12-05T21:00:02.000Z",
    "prevClose": 542.31,
    "high": 550.44,
    "low": 541.25,
    "volume": 1548968,
    "open": 541.71,
    "fiftyTwoWeekHigh": 601.77,
    "fiftyTwoWeekLow": 465.59,
    "marketCap": 493156564992,
    "peRatio": 34.83525,
    "eps": 15.66,
    "dividendYield": 0.0056056497,
    "lastUpdated": "2025-12-07T12:33:54.424Z"
  },
  {
    "symbol": "WMT",
    "name": "Walmart",
    "category": "Global",
    "country": "🇺🇸",
    "sector": null,
    "regularMarketPrice": 115.11,
    "price": 115.11,
    "regularMarketChange": 0.270004,
    "change": 0.270004,
    "regularMarketChangePercent": 0.235113,
    "changePercent": 0.235113,
    "regularMarketTime": "2025-12-05T21:00:02.000Z",
    "prevClose": 114.84,
    "high": 116.27,
    "low": 114.675,
    "volume": 23056950,
    "open": 114.73,
    "fiftyTwoWeekHigh": 116.27,
    "fiftyTwoWeekLow": 79.81,
    "marketCap": 917754937344,
    "peRatio": 40.389477,
    "eps": 2.85,
    "dividendYield": 0.007950191,
    "lastUpdated": "2025-12-07T12:33:54.424Z"
  },
  {
    "symbol": "HD",
    "name": "Home Depot",
    "category": "Global",
    "country": "🇺🇸",
    "sector": null,
    "regularMarketPrice": 354.61,
    "price": 354.61,
    "regularMarketChange": 3.43997,
    "change": 3.43997,
    "regularMarketChangePercent": 0.979575,
    "changePercent": 0.979575,
    "regularMarketTime": "2025-12-05T21:00:02.000Z",
    "prevClose": 351.17,
    "high": 355.62,
    "low": 349.525,
    "volume": 4495144,
    "open": 350.65,
    "fiftyTwoWeekHigh": 436.36,
    "fiftyTwoWeekLow": 326.31,
    "marketCap": 353018314752,
    "peRatio": 24.20546,
    "eps": 14.65,
    "dividendYield": 0.026198136,
    "lastUpdated": "2025-12-07T12:33:54.424Z"
  },
  {
    "symbol": "PG",
    "name": "P&G",
    "category": "Global",
    "country": "🇺🇸",
    "sector": null,
    "regularMarketPrice": 143.45,
    "price": 143.45,
    "regularMarketChange": -1.91,
    "change": -1.91,
    "regularMarketChangePercent": -1.31398,
    "changePercent": -1.31398,
    "regularMarketTime": "2025-12-05T21:00:16.000Z",
    "prevClose": 145.36,
    "high": 145.62,
    "low": 143.25,
    "volume": 11002888,
    "open": 145.16,
    "fiftyTwoWeekHigh": 179.99,
    "fiftyTwoWeekLow": 142.51,
    "marketCap": 335742631936,
    "peRatio": 20.911077,
    "eps": 6.86,
    "dividendYield": 0.02839158,
    "lastUpdated": "2025-12-07T12:33:54.424Z"
  },
  {
    "symbol": "KO",
    "name": "Coca-Cola",
    "category": "Global",
    "country": "🇺🇸",
    "sector": null,
    "regularMarketPrice": 70,
    "price": 70,
    "regularMarketChange": -0.449997,
    "change": -0.449997,
    "regularMarketChangePercent": -0.638747,
    "changePercent": -0.638747,
    "regularMarketTime": "2025-12-05T21:00:02.000Z",
    "prevClose": 70.45,
    "high": 70.71,
    "low": 69.8735,
    "volume": 13870404,
    "open": 70.315,
    "fiftyTwoWeekHigh": 74.38,
    "fiftyTwoWeekLow": 60.62,
    "marketCap": 301256704000,
    "peRatio": 23.178808,
    "eps": 3.02,
    "dividendYield": 0.028601848,
    "lastUpdated": "2025-12-07T12:33:54.424Z"
  },
  {
    "symbol": "PEP",
    "name": "PepsiCo",
    "category": "Global",
    "country": "🇺🇸",
    "sector": null,
    "regularMarketPrice": 145.02,
    "price": 145.02,
    "regularMarketChange": -0.467499,
    "change": -0.467499,
    "regularMarketChangePercent": -0.321333,
    "changePercent": -0.321333,
    "regularMarketTime": "2025-12-05T21:00:00.000Z",
    "prevClose": 145.4875,
    "high": 145.8,
    "low": 144.51,
    "volume": 5939360,
    "open": 145.63,
    "fiftyTwoWeekHigh": 161.5,
    "fiftyTwoWeekLow": 127.6,
    "marketCap": 198543589376,
    "peRatio": 27.570341,
    "eps": 5.26,
    "dividendYield": 0.03818197,
    "lastUpdated": "2025-12-07T12:33:54.424Z"
  },
  {
    "symbol": "DIS",
    "name": "Disney",
    "category": "Global",
    "country": "🇺🇸",
    "sector": null,
    "regularMarketPrice": 105.3,
    "price": 105.3,
    "regularMarketChange": -0.169998,
    "change": -0.169998,
    "regularMarketChangePercent": -0.161182,
    "changePercent": -0.161182,
    "regularMarketTime": "2025-12-05T21:00:10.000Z",
    "prevClose": 105.47,
    "high": 106.17,
    "low": 104.56,
    "volume": 8030156,
    "open": 105.18,
    "fiftyTwoWeekHigh": 124.69,
    "fiftyTwoWeekLow": 80.1,
    "marketCap": 189322444800,
    "peRatio": 15.349854,
    "eps": 6.86,
    "dividendYield": 0.014222054,
    "lastUpdated": "2025-12-07T12:33:54.424Z"
  },
  {
    "symbol": "NKE",
    "name": "Nike",
    "category": "Global",
    "country": "🇺🇸",
    "sector": null,
    "regularMarketPrice": 65.86,
    "price": 65.86,
    "regularMarketChange": 0.169998,
    "change": 0.169998,
    "regularMarketChangePercent": 0.258788,
    "changePercent": 0.258788,
    "regularMarketTime": "2025-12-05T21:00:02.000Z",
    "prevClose": 65.69,
    "high": 66.08,
    "low": 64.88,
    "volume": 9547105,
    "open": 65.7,
    "fiftyTwoWeekHigh": 82.44,
    "fiftyTwoWeekLow": 52.28,
    "marketCap": 97354342400,
    "peRatio": 33.774357,
    "eps": 1.95,
    "dividendYield": 0.024356827,
    "lastUpdated": "2025-12-07T12:33:54.424Z"
  },
  {
    "symbol": "COMI.CA",
    "name": "CIB Bank",
    "category": "EG",
    "country": "🇪🇬",
    "sector": "Financial",
    "regularMarketPrice": 81.2,
    "price": 81.2,
    "regularMarketChange": 0.5999985,
    "change": 0.5999985,
    "regularMarketChangePercent": 0.744415,
    "changePercent": 0.744415,
    "regularMarketTime": "2024-07-23T20:00:00.000Z",
    "prevClose": 80.6,
    "high": 81.2,
    "low": 81.2,
    "volume": 2359208,
    "open": 81.2,
    "fiftyTwoWeekHigh": 118.23,
    "fiftyTwoWeekLow": 73,
    "marketCap": 243391709184,
    "peRatio": 3.662607,
    "eps": 22.17,
    "dividendYield": 0,
    "lastUpdated": "2025-12-07T12:33:54.424Z"
  },
  {
    "symbol": "EAST.CA",
    "name": "Eastern Co",
    "category": "EG",
    "country": "🇪🇬",
    "sector": "Consumer",
    "regularMarketPrice": 21.8,
    "price": 21.8,
    "regularMarketChange": 0.55999947,
    "change": 0.55999947,
    "regularMarketChangePercent": 2.6365323,
    "changePercent": 2.6365323,
    "regularMarketTime": "2024-07-23T20:00:00.000Z",
    "prevClose": 21.24,
    "high": 21.8,
    "low": 21.8,
    "volume": 762933,
    "open": 21.8,
    "fiftyTwoWeekHigh": 49.99,
    "fiftyTwoWeekLow": 24,
    "marketCap": 65399996416,
    "peRatio": 6.728395,
    "eps": 3.24,
    "dividendYield": 0.13418078,
    "lastUpdated": "2025-12-07T12:33:54.424Z"
  },
  {
    "symbol": "HRHO.CA",
    "name": "EFG Hermes",
    "category": "EG",
    "country": "🇪🇬",
    "sector": "Financial",
    "regularMarketPrice": 21.55,
    "price": 21.55,
    "regularMarketChange": 0.32999992,
    "change": 0.32999992,
    "regularMarketChangePercent": 1.5551363,
    "changePercent": 1.5551363,
    "regularMarketTime": "2024-07-23T20:00:00.000Z",
    "prevClose": 21.22,
    "high": 21.55,
    "low": 21.55,
    "volume": 6268836,
    "open": 21.55,
    "fiftyTwoWeekHigh": 31.89,
    "fiftyTwoWeekLow": 19.2,
    "marketCap": 30943492096,
    "peRatio": 8.132075,
    "eps": 2.65,
    "dividendYield": 0,
    "lastUpdated": "2025-12-07T12:33:54.424Z"
  },
  {
    "symbol": "TMGH.CA",
    "name": "TMG Holding",
    "category": "EG",
    "country": "🇪🇬",
    "sector": "Real Estate",
    "regularMarketPrice": 58,
    "price": 58,
    "regularMarketChange": -0.6800003,
    "change": -0.6800003,
    "regularMarketChangePercent": -1.158828,
    "changePercent": -1.158828,
    "regularMarketTime": "2024-07-23T20:00:00.000Z",
    "prevClose": 58.68,
    "high": 58,
    "low": 58,
    "volume": 2690547,
    "open": 58,
    "fiftyTwoWeekHigh": 79.43,
    "fiftyTwoWeekLow": 46.75,
    "marketCap": 119517921280,
    "peRatio": 7.7540107,
    "eps": 7.48,
    "dividendYield": 0.004260395,
    "lastUpdated": "2025-12-07T12:33:54.424Z"
  },
  {
    "symbol": "SWDY.CA",
    "name": "Elsewedy",
    "category": "EG",
    "country": "🇪🇬",
    "sector": "Industrial",
    "regularMarketPrice": 47.69,
    "price": 47.69,
    "regularMarketChange": 0.20999908,
    "change": 0.20999908,
    "regularMarketChangePercent": 0.44228956,
    "changePercent": 0.44228956,
    "regularMarketTime": "2024-07-23T20:00:00.000Z",
    "prevClose": 47.48,
    "high": 47.69,
    "low": 47.69,
    "volume": 278148,
    "open": 47.69,
    "fiftyTwoWeekHigh": 92.2,
    "fiftyTwoWeekLow": 70.02,
    "marketCap": 102025871360,
    "peRatio": 6.962044,
    "eps": 6.85,
    "dividendYield": 0.0210615,
    "lastUpdated": "2025-12-07T12:33:54.424Z"
  },
  {
    "symbol": "ETEL.CA",
    "name": "Telecom Egy",
    "category": "EG",
    "country": "🇪🇬",
    "sector": "Telecom",
    "regularMarketPrice": 32.77,
    "price": 32.77,
    "regularMarketChange": 0.3199997,
    "change": 0.3199997,
    "regularMarketChangePercent": 0.98613155,
    "changePercent": 0.98613155,
    "regularMarketTime": "2024-07-23T20:00:00.000Z",
    "prevClose": 32.45,
    "high": 32.77,
    "low": 32.77,
    "volume": 827482,
    "open": 32.77,
    "fiftyTwoWeekHigh": 68.48,
    "fiftyTwoWeekLow": 32.41,
    "marketCap": 55940739072,
    "peRatio": 3.3853304,
    "eps": 9.68,
    "dividendYield": 0.04622496,
    "lastUpdated": "2025-12-07T12:33:54.424Z"
  },
  {
    "symbol": "AMOC.CA",
    "name": "AMOC",
    "category": "EG",
    "country": "🇪🇬",
    "sector": "Energy",
    "regularMarketPrice": 9.08,
    "price": 9.08,
    "regularMarketChange": -0.020000458,
    "change": -0.020000458,
    "regularMarketChangePercent": -0.21978524,
    "changePercent": -0.21978524,
    "regularMarketTime": "2024-07-23T20:00:00.000Z",
    "prevClose": 9.1,
    "high": 9.08,
    "low": 9.08,
    "volume": 2592903,
    "open": 9.08,
    "fiftyTwoWeekHigh": 8.39,
    "fiftyTwoWeekLow": 6.66,
    "marketCap": 11726820352,
    "peRatio": 7.8956523,
    "eps": 1.15,
    "dividendYield": 0.08791208,
    "lastUpdated": "2025-12-07T12:33:54.424Z"
  },
  {
    "symbol": "EKHO.CA",
    "name": "Egypt Kuwait",
    "category": "EG",
    "country": "🇪🇬",
    "sector": "Financial",
    "regularMarketPrice": 0.78,
    "price": 0.78,
    "regularMarketChange": -0.01000005,
    "change": -0.01000005,
    "regularMarketChangePercent": -1.2658291,
    "changePercent": -1.2658291,
    "regularMarketTime": "2024-07-23T20:00:00.000Z",
    "prevClose": 0.79,
    "high": 0.78,
    "low": 0.78,
    "volume": 162555,
    "open": 0.78,
    "fiftyTwoWeekHigh": 0.835,
    "fiftyTwoWeekLow": 0.627,
    "marketCap": 916443008,
    "peRatio": 6.5,
    "eps": 0.12,
    "dividendYield": 0.04177215,
    "lastUpdated": "2025-12-07T12:33:54.424Z"
  },
  {
    "symbol": "HELI.CA",
    "name": "Heliopolis",
    "category": "EG",
    "country": "🇪🇬",
    "sector": "Real Estate",
    "regularMarketPrice": 10.3,
    "price": 10.3,
    "regularMarketChange": 0.27999973,
    "change": 0.27999973,
    "regularMarketChangePercent": 2.7944083,
    "changePercent": 2.7944083,
    "regularMarketTime": "2024-07-23T20:00:00.000Z",
    "prevClose": 10.02,
    "high": 10.3,
    "low": 10.3,
    "volume": 20452488,
    "open": 10.3,
    "fiftyTwoWeekHigh": 11.93,
    "fiftyTwoWeekLow": 3.11,
    "marketCap": 41254133760,
    "peRatio": 4.327731,
    "eps": 2.38,
    "dividendYield": 0,
    "lastUpdated": "2025-12-07T12:33:54.424Z"
  },
  {
    "symbol": "ORAS.CA",
    "name": "Orascom",
    "category": "EG",
    "country": "🇪🇬",
    "sector": "Industrial",
    "regularMarketPrice": 71.05,
    "price": 71.05,
    "regularMarketChange": 0,
    "change": 0,
    "regularMarketChangePercent": 0,
    "changePercent": 0,
    "regularMarketTime": "2024-07-23T20:00:00.000Z",
    "prevClose": 71.05,
    "high": 71.05,
    "low": 71.05,
    "volume": 0,
    "open": 71.05,
    "fiftyTwoWeekHigh": 71.05,
    "fiftyTwoWeekLow": 71.05,
    "marketCap": 7832832000,
    "peRatio": 5.1937137,
    "eps": 13.68,
    "dividendYield": 0.0035186487,
    "lastUpdated": "2025-12-07T12:33:54.424Z"
  },
  {
    "symbol": "ESRS.CA",
    "name": "Ezz Steel",
    "category": "EG",
    "country": "🇪🇬",
    "sector": "Industrial",
    "regularMarketPrice": 83.2,
    "price": 83.2,
    "regularMarketChange": -0.069999695,
    "change": -0.069999695,
    "regularMarketChangePercent": -0.08406352,
    "changePercent": -0.08406352,
    "regularMarketTime": "2024-07-23T20:00:00.000Z",
    "prevClose": 83.27,
    "high": 83.2,
    "low": 83.2,
    "volume": 1046295,
    "open": 83.2,
    "fiftyTwoWeekHigh": 140,
    "fiftyTwoWeekLow": 56.8,
    "marketCap": 45123936256,
    "peRatio": 21.11675,
    "eps": 3.94,
    "dividendYield": 0,
    "lastUpdated": "2025-12-07T12:33:54.424Z"
  },
  {
    "symbol": "ABUK.CA",
    "name": "Abu Qir",
    "category": "EG",
    "country": "🇪🇬",
    "sector": "Industrial",
    "regularMarketPrice": 58.32,
    "price": 58.32,
    "regularMarketChange": -0.72999954,
    "change": -0.72999954,
    "regularMarketChangePercent": -1.2362397,
    "changePercent": -1.2362397,
    "regularMarketTime": "2024-07-23T20:00:00.000Z",
    "prevClose": 59.05,
    "high": 58.32,
    "low": 58.32,
    "volume": 994631,
    "open": 58.32,
    "fiftyTwoWeekHigh": 61.9,
    "fiftyTwoWeekLow": 45.01,
    "marketCap": 73592594432,
    "peRatio": 9.227848,
    "eps": 6.32,
    "dividendYield": 0.101608805,
    "lastUpdated": "2025-12-07T12:33:54.424Z"
  },
  {
    "symbol": "MFPC.CA",
    "name": "MOPCO",
    "category": "EG",
    "country": "🇪🇬",
    "sector": "Industrial",
    "regularMarketPrice": 43.8,
    "price": 43.8,
    "regularMarketChange": 0.88000107,
    "change": 0.88000107,
    "regularMarketChangePercent": 2.0503287,
    "changePercent": 2.0503287,
    "regularMarketTime": "2024-07-23T20:00:00.000Z",
    "prevClose": 42.92,
    "high": 43.8,
    "low": 43.8,
    "volume": 533339,
    "open": 43.8,
    "fiftyTwoWeekHigh": 43.68,
    "fiftyTwoWeekLow": 26.55,
    "marketCap": 125624541184,
    "peRatio": 11.711229,
    "eps": 3.74,
    "dividendYield": 0.059109975,
    "lastUpdated": "2025-12-07T12:33:54.424Z"
  },
  {
    "symbol": "ISPH.CA",
    "name": "Ibnsina",
    "category": "EG",
    "country": "🇪🇬",
    "sector": "Healthcare",
    "regularMarketPrice": 3.01,
    "price": 3.01,
    "regularMarketChange": 0.00999999,
    "change": 0.00999999,
    "regularMarketChangePercent": 0.33333302,
    "changePercent": 0.33333302,
    "regularMarketTime": "2024-07-23T20:00:00.000Z",
    "prevClose": 3,
    "high": 3.01,
    "low": 3.01,
    "volume": 4395239,
    "open": 3.01,
    "fiftyTwoWeekHigh": 12.3,
    "fiftyTwoWeekLow": 5.85,
    "marketCap": 3034080000,
    "peRatio": 4.362319,
    "eps": 0.69,
    "dividendYield": 0.05333333,
    "lastUpdated": "2025-12-07T12:33:54.424Z"
  },
  {
    "symbol": "PHDC.CA",
    "name": "Palm Hills",
    "category": "EG",
    "country": "🇪🇬",
    "sector": "Real Estate",
    "regularMarketPrice": 4.72,
    "price": 4.72,
    "regularMarketChange": 0.01999998,
    "change": 0.01999998,
    "regularMarketChangePercent": 0.42553154,
    "changePercent": 0.42553154,
    "regularMarketTime": "2024-07-23T20:00:00.000Z",
    "prevClose": 4.7,
    "high": 4.72,
    "low": 4.72,
    "volume": 15405251,
    "open": 4.72,
    "fiftyTwoWeekHigh": 9.49,
    "fiftyTwoWeekLow": 5.93,
    "marketCap": 13498795008,
    "peRatio": 3.0849671,
    "eps": 1.53,
    "dividendYield": 0,
    "lastUpdated": "2025-12-07T12:33:54.424Z"
  },
  {
    "symbol": "CIEB.CA",
    "name": "Crédit Agri",
    "category": "EG",
    "country": "🇪🇬",
    "sector": "Financial",
    "regularMarketPrice": 20.28,
    "price": 20.28,
    "regularMarketChange": 0.460001,
    "change": 0.460001,
    "regularMarketChangePercent": 2.320893,
    "changePercent": 2.320893,
    "regularMarketTime": "2024-07-23T20:00:00.000Z",
    "prevClose": 19.82,
    "high": 20.28,
    "low": 20.28,
    "volume": 657804,
    "open": 20.28,
    "fiftyTwoWeekHigh": 23.19,
    "fiftyTwoWeekLow": 16,
    "marketCap": 25350000640,
    "peRatio": 3.5269566,
    "eps": 5.75,
    "dividendYield": 0.16145308,
    "lastUpdated": "2025-12-07T12:33:54.424Z"
  },
  {
    "symbol": "FWRY.CA",
    "name": "Fawry",
    "category": "EG",
    "country": "🇪🇬",
    "sector": "Tech",
    "regularMarketPrice": 6.82,
    "price": 6.82,
    "regularMarketChange": 0.07000017,
    "change": 0.07000017,
    "regularMarketChangePercent": 1.0370396,
    "changePercent": 1.0370396,
    "regularMarketTime": "2024-07-23T20:00:00.000Z",
    "prevClose": 6.75,
    "high": 6.82,
    "low": 6.82,
    "volume": 8213095,
    "open": 6.82,
    "fiftyTwoWeekHigh": 16.1,
    "fiftyTwoWeekLow": 7.88,
    "marketCap": 23232487424,
    "peRatio": 9.884058,
    "eps": 0.69,
    "dividendYield": 0,
    "lastUpdated": "2025-12-07T12:33:54.424Z"
  },
  {
    "symbol": "ADIB.CA",
    "name": "ADIB Egypt",
    "category": "EG",
    "country": "🇪🇬",
    "sector": "Financial",
    "regularMarketPrice": 37.89,
    "price": 37.89,
    "regularMarketChange": 2.209999,
    "change": 2.209999,
    "regularMarketChangePercent": 6.1939435,
    "changePercent": 6.1939435,
    "regularMarketTime": "2024-07-23T20:00:00.000Z",
    "prevClose": 35.68,
    "high": 37.89,
    "low": 37.89,
    "volume": 1997340,
    "open": 37.89,
    "fiftyTwoWeekHigh": 44.04,
    "fiftyTwoWeekLow": 20.01,
    "marketCap": 52209426432,
    "peRatio": 8.130901,
    "eps": 4.66,
    "dividendYield": 0,
    "lastUpdated": "2025-12-07T12:33:54.424Z"
  },
  {
    "symbol": "^EGX30.CA",
    "name": "EGX 30",
    "category": "EG",
    "country": "🇪🇬",
    "sector": "Index",
    "regularMarketPrice": 7182.8,
    "price": 7182.8,
    "regularMarketChange": 7182.8,
    "change": 7182.8,
    "regularMarketChangePercent": 0,
    "changePercent": 0,
    "regularMarketTime": "1970-01-01T00:00:00.000Z",
    "prevClose": 7182.8,
    "high": 7182.8,
    "low": 7182.8,
    "volume": 0,
    "open": 7182.8,
    "fiftyTwoWeekHigh": 0,
    "fiftyTwoWeekLow": 0,
    "lastUpdated": "2025-12-07T12:33:54.424Z"
  },
  {
    "symbol": "^CASE30",
    "name": "EGX 30 Price Return Index",
    "category": "EG",
    "country": "🇪🇬",
    "sector": null,
    "regularMarketPrice": 41754.1,
    "price": 41754.1,
    "regularMarketChange": 412.10156,
    "change": 412.10156,
    "regularMarketChangePercent": 0.9968109,
    "changePercent": 0.9968109,
    "regularMarketTime": "2025-12-07T12:14:59.000Z",
    "prevClose": 41342,
    "high": 41850.5,
    "low": 41499.1,
    "volume": 476273000,
    "open": 41557.4,
    "fiftyTwoWeekHigh": 41850.5,
    "fiftyTwoWeekLow": 41499.1,
    "lastUpdated": "2025-12-07T12:33:54.424Z"
  }
]